{
    "instrument": "e ot Inssrurment",
    "bank": "Canara Bank",
    "location": "Kompally",
    "postal_code": "500014",
    "date": "060522",
    "code": "2014MSHCY",
    "fsn": "FSN000254",
    "date_format": "DDMMYYY",
    "payee": "Pay Dauid Corbeil",
    "payee_type": "Or Bearer",
    "amount_text": "Rupees bya Nine Hundred and Eighy Seven",
    "amount_number": "6952",
    "account_number": "12688056400459004590",
    "note": "Payable at par at all our Branches In India",
    "signature_instruction": "Please sign above",
    "transaction_id": "00353250005048",
    "branch_code": "31"
}