{
    "amount": -500014,
    "validity": "three months",
    "bank": "Canara Bank",
    "branch": "Kompally",
    "branch_code": "500014",
    "date": "060522",
    "instrument_number": "2014MSHCY",
    "fsn": "FSN000254",
    "date_format": "DDMMYYY",
    "payee": "Chapin Auger",
    "payee_type": "Or Bearer",
    "amount_in_words": "Three Thousand Seven Hundred and Thirty",
    "code": "66t6",
    "serial_number": "01590259080489001590",
    "note": "Payable at par at all our Branches In India",
    "signature_instruction": "Please sign above",
    "transaction_id": "0035385000504",
    "unknown_number": 31
}