<?xml version="1.0" encoding="utf-8"?>
<!DOCTYPE annotation SYSTEM "annotation.dtd">
<annotation date="19/12/2007" author="Jouve">
  <source width="2472" height="3504">01866_Q.png</source>
  <document>Questionnaire</document>
  <scenario>Modification de contrat / Commande</scenario>
  <writer>POTTIER Mathieu</writer>
  <sender_person></sender_person>
  <sender_company></sender_company>
  <sender_tel></sender_tel>
  <sender_fax></sender_fax>
  <receiver_person></receiver_person>
  <receiver_company></receiver_company>
  <subject></subject>
  <date></date>
  <place></place>
  <box top_left_x="166" top_left_y="360" bottom_right_x="726" bottom_right_y="502">
       <type>Code d'envoi</type>
       <text>FPAGUM</text>
  </box>
  <box top_left_x="398" top_left_y="523" bottom_right_x="1211" bottom_right_y="630">
       <type>Nom</type>
       <text>POTTIER</text>
  </box>
  <box top_left_x="1405" top_left_y="523" bottom_right_x="2182" bottom_right_y="627">
       <type>Prénom</type>
       <text>Mathieu</text>
  </box>
  <box top_left_x="482" top_left_y="627" bottom_right_x="2187" bottom_right_y="721">
       <type>Adresse</type>
       <text>17, rue des Courlis</text>
  </box>
  <box top_left_x="559" top_left_y="729" bottom_right_x="979" bottom_right_y="836">
       <type>Code Postal</type>
       <text>68320</text>
  </box>
  <box top_left_x="1102" top_left_y="723" bottom_right_x="2190" bottom_right_y="833">
       <type>Ville</type>
       <text>RIEDWIHR</text>
  </box>
  <box top_left_x="365" top_left_y="841" bottom_right_x="1242" bottom_right_y="989">
       <type>Téléphone</type>
       <text>0376423461</text>
  </box>
  <box top_left_x="505" top_left_y="1110" bottom_right_x="2188" bottom_right_y="1226">
       <type>Catégorie Scénario</type>
       <text>Modification de contrat/Commande</text>
  </box>
  <box top_left_x="287" top_left_y="1221" bottom_right_x="2189" bottom_right_y="1404">
       <type>Objet Scénario</type>
       <text>changement concernant votre dernière\ncommande</text>
  </box>
  <box top_left_x="278" top_left_y="1400" bottom_right_x="2190" bottom_right_y="1590">
       <type>Complément Scénario</type>
       <text>Souhait d'annulation de commande\n</text>
  </box>
  <box top_left_x="906" top_left_y="1608" bottom_right_x="1547" bottom_right_y="1759">
       <type>Référence client</type>
       <text>HQCHB11</text>
  </box>
  <box top_left_x="580" top_left_y="1757" bottom_right_x="2197" bottom_right_y="1855">
       <type>Interlocuteur</type>
       <text>La Reboute</text>
  </box>
  <box top_left_x="491" top_left_y="1848" bottom_right_x="2197" bottom_right_y="1955">
       <type>Adresse Interlocuteur</type>
       <text>Le Village Neuf</text>
  </box>
  <box top_left_x="569" top_left_y="1947" bottom_right_x="1000" bottom_right_y="2066">
       <type>Code Postal Interlocuteur</type>
       <text>26210</text>
  </box>
  <box top_left_x="1135" top_left_y="1948" bottom_right_x="2197" bottom_right_y="2050">
       <type>Ville Interlocuteur</type>
       <text>EPINOUZE</text>
  </box>
  <box top_left_x="1051" top_left_y="2286" bottom_right_x="1266" bottom_right_y="2397">
       <type>Temps passé</type>
       <text>12</text>
  </box>
  <box top_left_x="896" top_left_y="2220" bottom_right_x="947" bottom_right_y="2276">
       <type>Stylo bille</type>
       <text></text>
  </box>
  <box top_left_x="1072" top_left_y="2221" bottom_right_x="1121" bottom_right_y="2273">
       <type>Stylo plume</type>
       <text></text>
  </box>
  <box top_left_x="1262" top_left_y="2223" bottom_right_x="1366" bottom_right_y="2273">
       <type>Stylo feutre</type>
       <text>x</text>
  </box>
  <box top_left_x="285" top_left_y="2692" bottom_right_x="333" bottom_right_y="2742">
       <type>Contribution postale</type>
       <text>x</text>
  </box>
  <box top_left_x="1594" top_left_y="2647" bottom_right_x="2196" bottom_right_y="2760">
       <type>Date d'envoi postal</type>
       <text>12 janvier 2007</text>
  </box>
  <box top_left_x="295" top_left_y="2786" bottom_right_x="345" bottom_right_y="2834">
       <type>Option Page de garde de fax</type>
       <text></text>
  </box>
  <box top_left_x="293" top_left_y="2881" bottom_right_x="344" bottom_right_y="2927">
       <type>Option envoi par fax</type>
       <text></text>
  </box>
  <box top_left_x="1736" top_left_y="2821" bottom_right_x="2189" bottom_right_y="2939">
       <type>Date d'envoi par fax</type>
       <text></text>
  </box>
  <box top_left_x="293" top_left_y="2972" bottom_right_x="345" bottom_right_y="3022">
       <type>Option envoi par courriel</type>
       <text></text>
  </box>
  <box top_left_x="1592" top_left_y="2941" bottom_right_x="2191" bottom_right_y="3044">
       <type>Date d'envoi par courriel</type>
       <text></text>
  </box>
  <box top_left_x="1733" top_left_y="3138" bottom_right_x="2000" bottom_right_y="3232">
       <type>Résolution</type>
       <text></text>
  </box>
  <box top_left_x="567" top_left_y="3163" bottom_right_x="618" bottom_right_y="3212">
       <type>Format PNG</type>
       <text></text>
  </box>
  <box top_left_x="773" top_left_y="3162" bottom_right_x="825" bottom_right_y="3213">
       <type>Format GIF</type>
       <text></text>
  </box>
  <box top_left_x="956" top_left_y="3163" bottom_right_x="1006" bottom_right_y="3213">
       <type>Format TIFF</type>
       <text></text>
  </box>
  <box top_left_x="1068" top_left_y="3038" bottom_right_x="2192" bottom_right_y="3140">
       <type>Marque et modèle scanner</type>
       <text></text>
  </box>
</annotation>
