<?xml version="1.0" encoding="utf-8"?>
<!DOCTYPE annotation SYSTEM "annotation.dtd">
<annotation date="19/12/2007" author="Jouve ">
  <source width="2470" height="3504">02509_L.png</source>
  <document>Lettre manuscrite</document>
  <scenario>Demande d'information</scenario>
  <writer>MAZE Claudine</writer>
  <sender_person>Madame MAZE Claudine</sender_person>
  <sender_company></sender_company>
  <sender_tel>+33(0)3.61.09.85.56</sender_tel>
  <sender_fax></sender_fax>
  <receiver_person></receiver_person>
  <receiver_company>Trésorerie des Impôts</receiver_company>
  <date>05/02/2007</date>
  <place>Dieulouard</place>
  <box top_left_x="49" top_left_y="61" bottom_right_x="999" bottom_right_y="694">
  <type>Coordonnées Expéditeur</type>
  <text>Madame MAZE Claudine\n11 Rue de la Source\n54380 DIEULOUARD\nTél : 03.61.09.85.56\nRéf Client : RWHPT 24</text>
  </box>
  <box top_left_x="1327" top_left_y="591" bottom_right_x="2391" bottom_right_y="1121">
  <type>Coordonnées Destinataire</type>
  <text>Trésorerie des Impôts\nMonsieur le Percepteur\nSt Julien - St Martin en Vercors\n26420 ST JULIEN EN VERCORS</text>
  </box>
  <box top_left_x="1346" top_left_y="1178" bottom_right_x="1975" bottom_right_y="1460">
  <type>Date, Lieu</type>
  <text>Dieulouard,\nLe 5 février 2007</text>
  </box>
  <box top_left_x="99" top_left_y="1502" bottom_right_x="873" bottom_right_y="1700">
  <type>Ouverture</type>
  <text>Monsieur le Percepteur,</text>
  </box>
  <box top_left_x="83" top_left_y="1735" bottom_right_x="1647" bottom_right_y="3436">
  <type>Corps de texte</type>
  <text>Le désespoir me force à vous écrire cette lettre afin de vous\ndemander clémence, car j'ai d'énormes difficultés pour procéder\nau paiement de mes impôts.\nLa mauvaise gestion des trois sociétés de mon mari et son\ndépart "prématuré" sans laisser d'adresse font que je suis dans\nd'énormes soucis financiers car mon endettement devient de\nplus en plus importants ainsi que le nombre de créanciers\nque mon cher mari m'a laissé.\nC'est pour cela que je vous serai extrêmement reconnaissante\nde bien vouloir m'accorder une remise gracieuse pour mes impôts.\nSi vous le souhaitez, nous pouvons nous rencontrer au moment qu'il\nvous conviendra le mieux afin que je vous présente "mon cas"\nplus en détail.\nDans l'attente, je vous prie de recevoir, Monsieur le Percepteur,\nl'expression de mes salutations distinguées.</text>
  </box>
  <box top_left_x="1182" top_left_y="1647" bottom_right_x="2444" bottom_right_y="3237">
  <type>Corps de texte</type>
  <text></text>
  </box>
  <box top_left_x="1670" top_left_y="3249" bottom_right_x="2269" bottom_right_y="3493">
  <type>Signature</type>
  <text></text>
  </box>
</annotation>
