<?xml version="1.0" encoding="utf-8"?>
<!DOCTYPE annotation SYSTEM "annotation.dtd">
<annotation date="21/12/2007" author="Jouve ">
  <source width="2476" height="3505">02511_F.png</source>
  <document>Fax</document>
  <scenario>Difficulté de paiement</scenario>
  <writer>GABORIAU Cyrielle</writer>
  <sender_person>Mme Cyrielle GABORIAU</sender_person>
  <sender_company>¤{Faculté des Lettres et Sciences Humaines/UPVD\nUniversité de Perpignan Via Domitia}¤</sender_company>
  <sender_tel>+33(0)0.33.04.68.66</sender_tel>
  <sender_fax>+33(0)0.33.04.68.66</sender_fax>
  <receiver_person></receiver_person>
  <receiver_company>EDF</receiver_company>
  <subject>Objet : Demande de remise gracieuse</subject>
  <date></date>
  <place></place>
  <box top_left_x="475" top_left_y="213" bottom_right_x="1023" bottom_right_y="413">
  <type>Expéditeur_organisme / Dactylographié</type>
  <text>UPVD\nUniversité de Perpignan Via Domitia</text>
  </box>
  <box top_left_x="1208" top_left_y="349" bottom_right_x="2358" bottom_right_y="429">
  <type>Expéditeur_organisme / Dactylographié</type>
  <text>Faculté des Lettres et Sciences Humaines</text>
  </box>
  <box top_left_x="1263" top_left_y="844" bottom_right_x="1647" bottom_right_y="914">
  <type>Autre / Dactylographié</type>
  <text>TELECOPIE</text>
  </box>
  <box top_left_x="600" top_left_y="1107" bottom_right_x="913" bottom_right_y="1175">
  <type>Expéditeur_autre / Dactylographié</type>
  <text>Expéditeur :</text>
  </box>
  <box top_left_x="592" top_left_y="1591" bottom_right_x="939" bottom_right_y="1659">
  <type>Destinataire_autre / Dactylographié</type>
  <text>Destinataire :</text>
  </box>
  <box top_left_x="602" top_left_y="1848" bottom_right_x="784" bottom_right_y="1919">
  <type>Objet / Dactylographié</type>
  <text>Objet :</text>
  </box>
  <box top_left_x="593" top_left_y="2054" bottom_right_x="852" bottom_right_y="2120">
  <type>Autre / Dactylographié</type>
  <text>Message :</text>
  </box>
  <box top_left_x="1035" top_left_y="1373" bottom_right_x="1146" bottom_right_y="1437">
  <type>Expéditeur_autre / Dactylographié</type>
  <text>Fax :</text>
  </box>
  <box top_left_x="1149" top_left_y="1373" bottom_right_x="1474" bottom_right_y="1437">
  <type>Expéditeur_fax / Dactylographié</type>
  <text>04 68 66 00 44</text>
  </box>
  <box top_left_x="1483" top_left_y="1478" bottom_right_x="1778" bottom_right_y="1543">
  <type>Date, Lieu / Dactylographié</type>
  <text>Perpignan, le</text>
  </box>
  <box top_left_x="1925" top_left_y="1875" bottom_right_x="2059" bottom_right_y="1951">
  <type>Autre / Dactylographié</type>
  <text>P.J. :</text>
  </box>
  <box top_left_x="69" top_left_y="3134" bottom_right_x="571" bottom_right_y="3242">
  <type>Expéditeur_autre / Dactylographié</type>
  <text>52, avenue Paul Alduy\n66860 Perpignan Cedex</text>
  </box>
  <box top_left_x="62" top_left_y="3260" bottom_right_x="141" bottom_right_y="3305">
  <type>Expéditeur_autre / Dactylographié</type>
  <text>Tél</text>
  </box>
  <box top_left_x="66" top_left_y="3309" bottom_right_x="143" bottom_right_y="3345">
  <type>Expéditeur_autre / Dactylographié</type>
  <text>Fax</text>
  </box>
  <box top_left_x="148" top_left_y="3258" bottom_right_x="541" bottom_right_y="3307">
  <type>Expéditeur_tél / Dactylographié</type>
  <text>00 33 (0)4 68 66 21 55</text>
  </box>
  <box top_left_x="151" top_left_y="3307" bottom_right_x="544" bottom_right_y="3349">
  <type>Expéditeur_fax / Dactylographié</type>
  <text>00 33 (0)4 68 66 00 44</text>
  </box>
  <box top_left_x="102" top_left_y="211" bottom_right_x="403" bottom_right_y="406">
  <type>Logo</type>
  <text></text>
  </box>
  <box top_left_x="926" top_left_y="1062" bottom_right_x="1654" bottom_right_y="1168">
  <type>Expéditeur_personne / Manuscrit</type>
  <text>Mme Cyrielle GABORIAU</text>
  </box>
  <box top_left_x="916" top_left_y="1176" bottom_right_x="1093" bottom_right_y="1327">
  <type>Expéditeur_autre / Manuscrit</type>
  <text>Quartier Costa Plana Les Genêts\n06320 CAP D'AIL</text>
  </box>
  <box top_left_x="972" top_left_y="1569" bottom_right_x="1156" bottom_right_y="1643">
  <type>Destinataire_organisme / Manuscrit</type>
  <text>EDF</text>
  </box>
  <box top_left_x="946" top_left_y="1649" bottom_right_x="1824" bottom_right_y="1758">
  <type>Destinataire_autre / Manuscrit</type>
  <text>19, rue de Friedolsheim\n67200 STRASBOURG</text>
  </box>
  <box top_left_x="1025" top_left_y="1759" bottom_right_x="1198" bottom_right_y="1813">
  <type>Destinataire_autre / Dactylographié</type>
  <text>Fax n°</text>
  </box>
  <box top_left_x="816" top_left_y="1831" bottom_right_x="1920" bottom_right_y="1920">
  <type>Objet / Manuscrit</type>
  <text>Demande de remise gracieuse</text>
  </box>
  <box top_left_x="1205" top_left_y="1596" bottom_right_x="1825" bottom_right_y="1719">
  <type>Destinataire_autre / Manuscrit</type>
  <text></text>
  </box>
  <box top_left_x="1131" top_left_y="1171" bottom_right_x="2084" bottom_right_y="1327">
  <type>Expéditeur_autre / Manuscrit</type>
  <text></text>
  </box>
  <box top_left_x="961" top_left_y="1206" bottom_right_x="1418" bottom_right_y="1325">
  <type>Expéditeur_autre / Manuscrit</type>
  <text></text>
  </box>
  <box top_left_x="1099" top_left_y="1056" bottom_right_x="1125" bottom_right_y="1199">
  <type>Expéditeur_personne / Manuscrit</type>
  <text></text>
  </box>
</annotation>
