<?xml version="1.0" encoding="utf-8"?>
<!DOCTYPE annotation SYSTEM "annotation.dtd">
<annotation date="19/12/2007" author="Jouve ">
  <source width="2476" height="3505">02674_L.png</source>
  <document>Lettre manuscrite</document>
  <scenario>Modification de contrat / Commande</scenario>
  <writer>CHAUVET Olivier</writer>
  <sender_person>CHAUVET Olivier</sender_person>
  <sender_company></sender_company>
  <sender_tel>+33()....</sender_tel>
  <sender_fax></sender_fax>
  <receiver_person></receiver_person>
  <receiver_company>Trésorerie des impôts</receiver_company>
  <subject>Objet : Demande de Mensualisation de l'impôt sur le revenu.</subject>
  <date>09/02/2007</date>
  <place>Paris</place>
  <box top_left_x="68" top_left_y="30" bottom_right_x="894" bottom_right_y="559">
  <type>Coordonnées Expéditeur</type>
  <text>CHAUVET Olivier\n43 rue du vieux Chaumont\n88200 St Nabord\nTél : 0360842701\n¤{ref/réf}¤ client : YOJWF08</text>
  </box>
  <box top_left_x="1846" top_left_y="91" bottom_right_x="2440" bottom_right_y="262">
  <type>Date, Lieu</type>
  <text>Paris le 9 février 2007</text>
  </box>
  <box top_left_x="1473" top_left_y="601" bottom_right_x="2032" bottom_right_y="875">
  <type>Coordonnées Destinataire</type>
  <text>Trésorerie des impôts\n18 rue Georges Melies\n79022 Niort</text>
  </box>
  <box top_left_x="76" top_left_y="848" bottom_right_x="1457" bottom_right_y="974">
  <type>Objet</type>
  <text>Objet : Demande de Mensualisation de l'impôt sur le revenu.</text>
  </box>
  <box top_left_x="342" top_left_y="1119" bottom_right_x="620" bottom_right_y="1229">
  <type>Ouverture</type>
  <text>Monsieur</text>
  </box>
  <box top_left_x="34" top_left_y="1263" bottom_right_x="2253" bottom_right_y="2398">
  <type>Corps de texte</type>
  <text>Suite aux difficultés rencontrées l'année dernière pour payer mes impôts et\nen raison de la précarité qui s'est installée à mon travail, j'aimerai pouvoir\nétaler le paiement de cette taxe. Cette mensualisation me permettrai de ne plus\nsubir les problèmes passés en raison du montant élevé à payer. Le ¤{paiment/paiement}¤\npar plus petites sommes serai pour moi un soulagement et même si cela\nserai plus régulier, je pourrai les payer avec moin de difficulter.\nVous remerciant par avance, je vous prie de croire, Monsieur, à mes\nsentiments distingués.</text>
  </box>
  <box top_left_x="905" top_left_y="2462" bottom_right_x="1617" bottom_right_y="2744">
  <type>Signature</type>
  <text></text>
  </box>
</annotation>
