<?xml version="1.0" encoding="utf-8"?>
<!DOCTYPE annotation SYSTEM "annotation.dtd">
<annotation date="19/12/2007" author="Jouve ">
  <source width="2469" height="3507">02845_L.png</source>
  <document>Lettre manuscrite</document>
  <scenario>Relance de courrier sans réponse</scenario>
  <writer>LE ROUZIC Jean-michel</writer>
  <sender_person>Le Rouzic Jean-Michel</sender_person>
  <sender_company></sender_company>
  <sender_tel>+33(0)3.66.11.38.27</sender_tel>
  <sender_fax></sender_fax>
  <receiver_person></receiver_person>
  <receiver_company>BAAF ASSURANCES</receiver_company>
  <subject>Objet : Attente d'une réponse...</subject>
  <date>15/02/2007</date>
  <place>Dossenheim/Zinsel</place>
  <box top_left_x="53" top_left_y="38" bottom_right_x="1102" bottom_right_y="663">
  <type>Coordonnées Expéditeur</type>
  <text>Le Rouzic Jean-Michel\n12, rue des Aubépines\n67330 Dossinheim/Zinsel\nTél : 03.66.11.38.27</text>
  </box>
  <box top_left_x="1311" top_left_y="720" bottom_right_x="2269" bottom_right_y="1167">
  <type>Coordonnées Destinataire</type>
  <text>BAAF ASSURANCES\nPlace des Tilleuls\n73240 ST GENIX/GUIERS</text>
  </box>
  <box top_left_x="122" top_left_y="1207" bottom_right_x="1262" bottom_right_y="1365">
  <type>Objet</type>
  <text>Objet : Attente d'une réponse...</text>
  </box>
  <box top_left_x="125" top_left_y="1371" bottom_right_x="1010" bottom_right_y="1522">
  <type>Coordonnées Expéditeur</type>
  <text>Réf : ZKMXW90</text>
  </box>
  <box top_left_x="1243" top_left_y="1495" bottom_right_x="2299" bottom_right_y="1681">
  <type>Date, Lieu</type>
  <text>Dossenheim/Zinsel, le 15/02/07</text>
  </box>
  <box top_left_x="858" top_left_y="1700" bottom_right_x="1559" bottom_right_y="1891">
  <type>Ouverture</type>
  <text>Madame, Monsieur,</text>
  </box>
  <box top_left_x="171" top_left_y="1922" bottom_right_x="1662" bottom_right_y="2974">
  <type>Corps de texte</type>
  <text>Suite au silence de vos services depuis plus d'un\nmois, concernant ma demande d'information du mois\ndernier, je me permets de me manifester à nouveau.\nSerait-il possible que l'un de vos conseillers me\ncontacte afin de m'informer dans les plus brefs délais ?\nDans l'attente d'une réponse rapide, veuillez agréer\nMadame, Monsieurs, mes salutations distinguées.</text>
  </box>
  <box top_left_x="1586" top_left_y="1872" bottom_right_x="2265" bottom_right_y="2928">
  <type>Corps de texte</type>
  <text></text>
  </box>
  <box top_left_x="1331" top_left_y="2990" bottom_right_x="1731" bottom_right_y="3329">
  <type>Signature</type>
  <text></text>
  </box>
  <box top_left_x="1674" top_left_y="2955" bottom_right_x="2040" bottom_right_y="3394">
  <type>Signature</type>
  <text></text>
  </box>
</annotation>
