<?xml version="1.0" encoding="utf-8"?>
<!DOCTYPE annotation SYSTEM "annotation.dtd">
<annotation date="21/12/2007" author="Jouve ">
  <source width="2471" height="3509">03096_F.png</source>
  <document>Fax</document>
  <scenario>Fermeture de compte</scenario>
  <writer>FERRIE Marion</writer>
  <sender_person>¤{Ferrie Marion/FERRIE Marion}¤</sender_person>
  <sender_company></sender_company>
  <sender_tel>+33(0)3.81.63.27.19</sender_tel>
  <sender_fax></sender_fax>
  <receiver_person></receiver_person>
  <receiver_company>Banque Crédit Populaire</receiver_company>
  <subject>Objet / référence : fermeture de compte</subject>
  <date>23/02/2007</date>
  <place></place>
  <box top_left_x="316" top_left_y="33" bottom_right_x="627" bottom_right_y="533">
  <type>Logo</type>
  <text>¤¤</text>
  </box>
  <box top_left_x="1030" top_left_y="569" bottom_right_x="1415" bottom_right_y="675">
  <type>Autre / Dactylographié</type>
  <text>Télécopie</text>
  </box>
  <box top_left_x="326" top_left_y="715" bottom_right_x="652" bottom_right_y="780">
  <type>Destinataire_autre / Dactylographié</type>
  <text>Destinataire :</text>
  </box>
  <box top_left_x="329" top_left_y="857" bottom_right_x="548" bottom_right_y="920">
  <type>Destinataire_autre / Dactylographié</type>
  <text>Société :</text>
  </box>
  <box top_left_x="319" top_left_y="993" bottom_right_x="869" bottom_right_y="1066">
  <type>Destinataire_autre / Dactylographié</type>
  <text>Numéro de télécopie :</text>
  </box>
  <box top_left_x="1223" top_left_y="712" bottom_right_x="1525" bottom_right_y="790">
  <type>Expéditeur_autre / Dactylographié</type>
  <text>Expéditeur :</text>
  </box>
  <box top_left_x="1222" top_left_y="857" bottom_right_x="1388" bottom_right_y="911">
  <type>Date, Lieu / Dactylographié</type>
  <text>Date :</text>
  </box>
  <box top_left_x="1218" top_left_y="988" bottom_right_x="1779" bottom_right_y="1051">
  <type>Expéditeur_autre / Dactylographié</type>
  <text>Numéro de téléphone :</text>
  </box>
  <box top_left_x="323" top_left_y="1124" bottom_right_x="1155" bottom_right_y="1188">
  <type>Autre / Dactylographié</type>
  <text>Nombre de pages (1ère page incluse) :</text>
  </box>
  <box top_left_x="1229" top_left_y="1124" bottom_right_x="1672" bottom_right_y="1177">
  <type>Objet / Dactylographié</type>
  <text>Objet / référence :</text>
  </box>
  <box top_left_x="328" top_left_y="1302" bottom_right_x="2156" bottom_right_y="1398">
  <type>Autre / Dactylographié</type>
  <text>¢Urgent ¥Pour avis ¥Commentaires ¥Réponse ¥Confidentiel</text>
  </box>
  <box top_left_x="982" top_left_y="242" bottom_right_x="1436" bottom_right_y="310">
  <type>Expéditeur_personne / Manuscrit</type>
  <text>FERRIE Marion</text>
  </box>
  <box top_left_x="988" top_left_y="319" bottom_right_x="1730" bottom_right_y="485">
  <type>Expéditeur_autre / Manuscrit</type>
  <text>13 rue de Chalonvillais\n90350 EVETTE SALBERT</text>
  </box>
  <box top_left_x="335" top_left_y="783" bottom_right_x="1120" bottom_right_y="838">
  <type>Destinataire_organisme / Manuscrit</type>
  <text>Banque Crédit Populaire</text>
  </box>
  <box top_left_x="1541" top_left_y="780" bottom_right_x="1923" bottom_right_y="843">
  <type>Expéditeur_personne / Manuscrit</type>
  <text>Ferrie Marion</text>
  </box>
  <box top_left_x="1244" top_left_y="913" bottom_right_x="1545" bottom_right_y="974">
  <type>Date, Lieu / Manuscrit</type>
  <text>23/02/07</text>
  </box>
  <box top_left_x="1246" top_left_y="1054" bottom_right_x="1744" bottom_right_y="1113">
  <type>Expéditeur_tél / Manuscrit</type>
  <text>03.81.63.27.19</text>
  </box>
  <box top_left_x="1249" top_left_y="1179" bottom_right_x="1852" bottom_right_y="1259">
  <type>Objet / Manuscrit</type>
  <text>fermeture de compte</text>
  </box>
  <box top_left_x="725" top_left_y="752" bottom_right_x="1111" bottom_right_y="819">
  <type>Destinataire_organisme / Manuscrit</type>
  <text></text>
  </box>
</annotation>
