<?xml version="1.0" encoding="utf-8"?>
<!DOCTYPE annotation SYSTEM "annotation.dtd">
<annotation date="19/12/2007" author="Jouve ">
  <source width="2473" height="3509">03179_L.png</source>
  <document>Lettre manuscrite</document>
  <scenario>Demande d'information</scenario>
  <writer>BEGUIN Geraldine</writer>
  <sender_person>Mme Beguin Géraldine</sender_person>
  <sender_company></sender_company>
  <sender_tel></sender_tel>
  <sender_fax></sender_fax>
  <receiver_person></receiver_person>
  <receiver_company>BAAF Assurances</receiver_company>
  <subject>Objet : Demande de documentation concernant les contrats d'assurance vie.</subject>
  <date>26/02/2007</date>
  <place>Neubois</place>
  <box top_left_x="26" top_left_y="64" bottom_right_x="694" bottom_right_y="347">
  <type>Coordonnées Expéditeur</type>
  <text>Mme Beguin Géraldine\n19 Rue Principale\n67220 NEUBOIS</text>
  </box>
  <box top_left_x="1231" top_left_y="22" bottom_right_x="1899" bottom_right_y="202">
  <type>Date, Lieu</type>
  <text>Le 26/02/07, Neubois</text>
  </box>
  <box top_left_x="1216" top_left_y="495" bottom_right_x="2150" bottom_right_y="827">
  <type>Coordonnées Destinataire</type>
  <text>BAAF Assurances\n10 Rue de la Poste\n08350 Noyers Pont Maugis</text>
  </box>
  <box top_left_x="30" top_left_y="861" bottom_right_x="2353" bottom_right_y="1064">
  <type>Objet</type>
  <text>Objet : Demande de documentation concernant les contrats d'assurance vie.</text>
  </box>
  <box top_left_x="305" top_left_y="1212" bottom_right_x="968" bottom_right_y="1403">
  <type>Ouverture</type>
  <text>Madame, Monsieur,</text>
  </box>
  <box top_left_x="167" top_left_y="1464" bottom_right_x="2437" bottom_right_y="2093">
  <type>Corps de texte</type>
  <text>Me mariant prochainement, je dois souscrire à d'une assurance couple.\nPouvez-vous m'envoyer de la documentation concernant les contrats\nd'assurance vie.\nJe vous en remercie d'avance.\nJe vous prie d'agréer, Madame, Monsieur, mes meilleures salutations</text>
  </box>
  <box top_left_x="1147" top_left_y="2330" bottom_right_x="1903" bottom_right_y="2677">
  <type>Signature</type>
  <text></text>
  </box>
</annotation>
