{
    "executiveReadingFile": {
        "inputForm": {
            "generalTopic": "Competitor Activities",
            "articleSubtopics": "PM",
            "articleTitle": "A NEW BLEND BEING TESTED",
            "author": "PHILIP MORRIS",
            "dateOfArticle": "08/28/84",
            "source": "B6w Report PCS-B074-84",
            "deletionDate": "",
            "otherComment": "",
            "nextUpdate": "",
            "limitDistributionTo": "",
            "criticalArticle": "",
            "articleText": "Copy of report is attached",
            "enteredDate": "",
            "phone": "787654044",
            "additionalInfo": "IFIIM IMAGE IS LESS CLEAR"
        }
    }
}