{
    "Code d'envoi": "HXXJLQ",
    "Nom": "Gineste",
    "Prénom": "Gérard",
    "Adresse": "1 impasse des Peupliers",
    "Code Postal": "9080¤6¤",
    "Ville": "Banvillars",
    "Téléphone": "0389314461",
    "Catégorie Scénario": "Relance de courrier sans réponse",
    "Objet Scénario": "Votre demande d'information est restée\\nsans effet",
    "Complément Scénario": "\\n",
    "Référence client": "ZMWDA29",
    "Interlocuteur": "BOF Telecom",
    "Adresse Interlocuteur": "17 Place St Jean",
    "Code Postal Interlocuteur": "34130",
    "Ville Interlocuteur": "Lansargues",
    "Temps passé": "20",
    "Stylo bille": "x",
    "Stylo plume": "",
    "Stylo feutre": "",
    "Contribution postale": "x",
    "Date d'envoi postal": "30/01/07",
    "Option Page de garde de fax": "",
    "Option envoi par fax": "",
    "Date d'envoi par fax": "",
    "Option envoi par courriel": "",
    "Date d'envoi par courriel": "",
    "Résolution": "",
    "Format PNG": "",
    "Format GIF": "",
    "Format TIFF": "",
    "Marque et modèle scanner": ""
}