{
    "Code d'envoi": "YLCAXZ",
    "Nom": "BONNEMAISON",
    "Prénom": "Lionnel",
    "Adresse": "33 rue de la 1ère armée",
    "Code Postal": "68790",
    "Ville": "MORSCHWILLER LE BAS",
    "Téléphone": "0339203082",
    "Catégorie Scénario": "Demande d'information",
    "Objet Scénario": "Demande de documentation concernant les contrats d'assurance\\nhabitation",
    "Complément Scénario": "Vous vous installez avec votre conjoint\\n",
    "Référence client": "YCORQ43",
    "Interlocuteur": "NAIF Assurances",
    "Adresse Interlocuteur": "centre commercial découverte",
    "Code Postal Interlocuteur": "35405",
    "Ville Interlocuteur": "ST MALO",
    "Temps passé": "25",
    "Stylo bille": "x",
    "Stylo plume": "",
    "Stylo feutre": "",
    "Contribution postale": "x",
    "Date d'envoi postal": "30/01/07",
    "Option Page de garde de fax": "x",
    "Option envoi par fax": "x",
    "Date d'envoi par fax": "30/01/07",
    "Option envoi par courriel": "x",
    "Date d'envoi par courriel": "30/01/07",
    "Résolution": "300",
    "Format PNG": "",
    "Format GIF": "",
    "Format TIFF": "x",
    "Marque et modèle scanner": "CANON MP 80"
}