{
    "Code d'envoi": "OFKZKQ",
    "Nom": "YON",
    "Prénom": "Géraldine",
    "Adresse": "14 Rue du 7 février",
    "Code Postal": "68740",
    "Ville": "BALGAU",
    "Téléphone": "0394382904",
    "Catégorie Scénario": "Fermeture de compte",
    "Objet Scénario": "Résiliation d'assurance habitation\\n",
    "Complément Scénario": "vous vendez votre habitation\\n",
    "Référence client": "JFCTN26",
    "Interlocuteur": "NNA Assurances",
    "Adresse Interlocuteur": "11 Route Nationale 43",
    "Code Postal Interlocuteur": "62890",
    "Ville Interlocuteur": "ZOUAFQUES",
    "Temps passé": "10",
    "Stylo bille": "x",
    "Stylo plume": "",
    "Stylo feutre": "",
    "Contribution postale": "x",
    "Date d'envoi postal": "1/02/07",
    "Option Page de garde de fax": "",
    "Option envoi par fax": "",
    "Date d'envoi par fax": "",
    "Option envoi par courriel": "x",
    "Date d'envoi par courriel": "1/02/07",
    "Résolution": "200",
    "Format PNG": "x",
    "Format GIF": "",
    "Format TIFF": "",
    "Marque et modèle scanner": "CANON Canoscan N1220U"
}