{
    "Code d'envoi": "CQOFKX",
    "Nom": "SCHMITT",
    "Prénom": "Maryse",
    "Adresse": "Ferme de Marimbois",
    "Code Postal": "54470",
    "Ville": "DAMPVITOUX",
    "Téléphone": "0347256741",
    "Catégorie Scénario": "Ouverture de compte",
    "Objet Scénario": "Vous souhaitez connaître la marche à suivre\\npour devenir client",
    "Complément Scénario": "Aucun\\n",
    "Référence client": "",
    "Interlocuteur": "NAIF Assurances",
    "Adresse Interlocuteur": "11 Route Nationale 43",
    "Code Postal Interlocuteur": "62890",
    "Ville Interlocuteur": "ZOUAFQUES",
    "Temps passé": "25",
    "Stylo bille": "x",
    "Stylo plume": "",
    "Stylo feutre": "",
    "Contribution postale": "x",
    "Date d'envoi postal": "7 février 2007",
    "Option Page de garde de fax": "",
    "Option envoi par fax": "",
    "Date d'envoi par fax": "",
    "Option envoi par courriel": "",
    "Date d'envoi par courriel": "",
    "Résolution": "",
    "Format PNG": "",
    "Format GIF": "",
    "Format TIFF": "",
    "Marque et modèle scanner": ""
}