{
    "Code d'envoi": "GFFAQS",
    "Nom": "GUENARO",
    "Prénom": "FRANCE",
    "Adresse": "87 RUE DE LORRAINE",
    "Code Postal": "57690",
    "Ville": "ELVANGE",
    "Téléphone": "0369601726",
    "Catégorie Scénario": "Modification de contrat/commande",
    "Objet Scénario": "Commande de trois paires de chaussettes\\n(référence produit : CH45-12)",
    "Complément Scénario": "aucun\\n",
    "Référence client": "WKAEN02",
    "Interlocuteur": "Les 3 Suifs",
    "Adresse Interlocuteur": "AU BOURG",
    "Code Postal Interlocuteur": "74500",
    "Ville Interlocuteur": "VINZIER",
    "Temps passé": "15",
    "Stylo bille": "x",
    "Stylo plume": "",
    "Stylo feutre": "",
    "Contribution postale": "x",
    "Date d'envoi postal": "05/02/2007",
    "Option Page de garde de fax": "",
    "Option envoi par fax": "",
    "Date d'envoi par fax": "",
    "Option envoi par courriel": "",
    "Date d'envoi par courriel": "",
    "Résolution": "",
    "Format PNG": "",
    "Format GIF": "",
    "Format TIFF": "",
    "Marque et modèle scanner": ""
}