{
    "Code d'envoi": "VIZJYO",
    "Nom": "RABHI",
    "Prénom": "Ludivine",
    "Adresse": "35 VACQUEMOUX",
    "Code Postal": "67130",
    "Ville": "LA BROQUE",
    "Téléphone": "0345597276",
    "Catégorie Scénario": "OUVERTURE DE COMPTE",
    "Objet Scénario": "VOUS SOUHAITEZ CONNAITRE LA MARCHE A SUIVRE POUR\\nDEVENIR CLIENT",
    "Complément Scénario": "\\n",
    "Référence client": "",
    "Interlocuteur": "LES 3 SUIFS",
    "Adresse Interlocuteur": "LE VILLAGE",
    "Code Postal Interlocuteur": "26400",
    "Ville Interlocuteur": "MIRABEL ET BLACONS",
    "Temps passé": "10",
    "Stylo bille": "x",
    "Stylo plume": "",
    "Stylo feutre": "",
    "Contribution postale": "x",
    "Date d'envoi postal": "22/02/2007",
    "Option Page de garde de fax": "",
    "Option envoi par fax": "x",
    "Date d'envoi par fax": "",
    "Option envoi par courriel": "",
    "Date d'envoi par courriel": "22/02/2007",
    "Résolution": "",
    "Format PNG": "",
    "Format GIF": "",
    "Format TIFF": "",
    "Marque et modèle scanner": ""
}