{
    "Code d'envoi": "ASKKIR",
    "Nom": "COLOMBO",
    "Prénom": "Pablo",
    "Adresse": "561 Chemin des Launes Clos Friquette",
    "Code Postal": "06910",
    "Ville": "AIGLUN",
    "Téléphone": "0451839283",
    "Catégorie Scénario": "Gestion de sinistre",
    "Objet Scénario": "Vous souhaitez être couvert du titre de la\\nresponsabilité civile",
    "Complément Scénario": "Vous avez brisé la porte vitrée d'un magasin en passant au travers\\nmagasin en passant au travers",
    "Référence client": "ULEOD74",
    "Interlocuteur": "NAIF Assurances",
    "Adresse Interlocuteur": "SAINT LEONS",
    "Code Postal Interlocuteur": "12780",
    "Ville Interlocuteur": "ST LEONS",
    "Temps passé": "10",
    "Stylo bille": "x",
    "Stylo plume": "",
    "Stylo feutre": "",
    "Contribution postale": "x",
    "Date d'envoi postal": "13/03/07",
    "Option Page de garde de fax": "",
    "Option envoi par fax": "",
    "Date d'envoi par fax": "",
    "Option envoi par courriel": "",
    "Date d'envoi par courriel": "",
    "Résolution": "",
    "Format PNG": "",
    "Format GIF": "",
    "Format TIFF": "",
    "Marque et modèle scanner": ""
}