{
    "Code d'envoi": "TKAFBU",
    "Nom": "FERDINAND",
    "Prénom": "Anne",
    "Adresse": "240 Rue MAURICE COLLIN",
    "Code Postal": "88140",
    "Ville": "CONTREXEVILLE",
    "Téléphone": "0393118699",
    "Catégorie Scénario": "Modification de contrat / commande",
    "Objet Scénario": "Demande de mensualisation de l'impôt\\n",
    "Complément Scénario": "\\n",
    "Référence client": "WSVNZ29",
    "Interlocuteur": "¤{Tresorie/Trésorerie}¤ des impôts",
    "Adresse Interlocuteur": "Chef lieu",
    "Code Postal Interlocuteur": "73600",
    "Ville Interlocuteur": "ST MARCEL",
    "Temps passé": "5",
    "Stylo bille": "x",
    "Stylo plume": "",
    "Stylo feutre": "",
    "Contribution postale": "x",
    "Date d'envoi postal": "8/3/07",
    "Option Page de garde de fax": "x",
    "Option envoi par fax": "x",
    "Date d'envoi par fax": "7/3/07",
    "Option envoi par courriel": "x",
    "Date d'envoi par courriel": "7/3/07",
    "Résolution": "300",
    "Format PNG": "",
    "Format GIF": "",
    "Format TIFF": "x",
    "Marque et modèle scanner": "EPSON Stylus CX 3200"
}