<?xml version="1.0" encoding="utf-8"?>
<!DOCTYPE annotation SYSTEM "annotation.dtd">
<annotation date="19/12/2007" author="Jouve ">
  <source width="2472" height="3505">00044_L.png</source>
  <document>Lettre manuscrite</document>
  <scenario>Relance de courrier sans réponse</scenario>
  <writer>PALMA Sylvie</writer>
  <sender_person>PALMA Sylvie</sender_person>
  <sender_company></sender_company>
  <sender_tel>+33(0)3.68.31.66.50</sender_tel>
  <sender_fax></sender_fax>
  <receiver_person></receiver_person>
  <receiver_company>NNA Assurances</receiver_company>
  <date>09/08/2006</date>
  <place>Nonzeville</place>
  <box top_left_x="3" top_left_y="133" bottom_right_x="966" bottom_right_y="681">
  <type>Coordonnées Expéditeur</type>
  <text>PALMA Sylvie\n4, route de destord\n88600 Nonzeville\nTel : 03 68 31 66 50</text>
  </box>
  <box top_left_x="15" top_left_y="1180" bottom_right_x="833" bottom_right_y="1336">
  <type>Coordonnées Expéditeur</type>
  <text>Ref. Client : EGXFU 76</text>
  </box>
  <box top_left_x="1024" top_left_y="905" bottom_right_x="2127" bottom_right_y="1305">
  <type>Coordonnées Destinataire</type>
  <text>NNA Assurances\n10, rue Alfred Lanel\n27500 Port Audener</text>
  </box>
  <box top_left_x="837" top_left_y="1397" bottom_right_x="2078" bottom_right_y="1568">
  <type>Date, Lieu</type>
  <text>Nonzeville, le 9 aout 2006</text>
  </box>
  <box top_left_x="38" top_left_y="1598" bottom_right_x="856" bottom_right_y="1777">
  <type>Ouverture</type>
  <text>Madame, Monsieur,</text>
  </box>
  <box top_left_x="26" top_left_y="1808" bottom_right_x="1050" bottom_right_y="2999">
  <type>Corps de texte</type>
  <text>Par la ¤{presente/présente}¤, je me permets de vous relancer suite\nà mon courrier du mois dernier resté sans réponse.\nJe vous informais ds ce dernier de mon changement\nde domicile et vous demandais un devis\npour ma nouvelle maison. Ces ¤{caracteristique/caractéristique}¤ sont\nles suivantes : 234 m2, maison du 18ème siècle, sans\nvolets.\nMerci par avance pour votre réponse. Respectueuses\nsalutations</text>
  </box>
  <box top_left_x="955" top_left_y="1838" bottom_right_x="2440" bottom_right_y="2877">
  <type>Corps de texte</type>
  <text></text>
  </box>
  <box top_left_x="1096" top_left_y="2896" bottom_right_x="1914" bottom_right_y="3330">
  <type>Signature</type>
  <text></text>
  </box>
</annotation>
