<?xml version="1.0" encoding="utf-8"?>
<!DOCTYPE annotation SYSTEM "annotation.dtd">
<annotation date="19/12/2007" author="Jouve ">
  <source width="2468" height="3503">00376_L.png</source>
  <document>Lettre manuscrite</document>
  <scenario>Modification de contrat / Commande</scenario>
  <writer>GALLIER Gilbert</writer>
  <sender_person>Gallin Gilbert</sender_person>
  <sender_company></sender_company>
  <sender_tel></sender_tel>
  <sender_fax></sender_fax>
  <receiver_person></receiver_person>
  <receiver_company>trésorerie des impots</receiver_company>
  <date></date>
  <place></place>
  <box top_left_x="30" top_left_y="101" bottom_right_x="950" bottom_right_y="429">
  <type>Coordonnées Expéditeur</type>
  <text>Gallien Gilbert\n16 rue du moulin\n57300 Ay sur moselle</text>
  </box>
  <box top_left_x="1644" top_left_y="422" bottom_right_x="2462" bottom_right_y="788">
  <type>Coordonnées Destinataire</type>
  <text>trésorerie des ¤{}¤impots/impôts\n1 Boulevard Maurice Violette\n28000 Chartres</text>
  </box>
  <box top_left_x="741" top_left_y="886" bottom_right_x="1701" bottom_right_y="1062">
  <type>Ouverture</type>
  <text>Monsieur l'inspecteur,</text>
  </box>
  <box top_left_x="217" top_left_y="1154" bottom_right_x="2428" bottom_right_y="2217">
  <type>Corps de texte</type>
  <text>Je me permet de vous écrire pour\nla modification de mon contrat.\nEn effet, j'aimerai faire une demande\nde mensualisation de l'¤{}¤impot/impôt sur le\nrevenu.\nVeuillez agréer mes salutations distingués.</text>
  </box>
  <box top_left_x="1697" top_left_y="2391" bottom_right_x="2172" bottom_right_y="2643">
  <type>Signature</type>
  <text></text>
  </box>
</annotation>
