<?xml version="1.0" encoding="utf-8"?>
<!DOCTYPE annotation SYSTEM "annotation.dtd">
<annotation date="21/12/2007" author="Jouve ">
  <source width="2471" height="3509">00493_F.png</source>
  <document>Fax</document>
  <scenario>Fermeture de compte</scenario>
  <writer>LONGUET Gerard</writer>
  <sender_person>Gérard LONGUET</sender_person>
  <sender_company>L.M.A.R.C.\nLaboratoire de Mécanique Appliquée R. Chaléat</sender_company>
  <sender_tel>+33(0)3.81.66.60.00</sender_tel>
  <sender_fax>+33(0)3.81.66.67.00</sender_fax>
  <receiver_person></receiver_person>
  <receiver_company>MANIF Assurances</receiver_company>
  <subject>Objet : résiliation d'assurance automobile</subject>
  <date>05/10/2006</date>
  <place></place>
  <box top_left_x="864" top_left_y="299" bottom_right_x="1551" bottom_right_y="398">
  <type>Autre / Dactylographié</type>
  <text>TELECOPIE</text>
  </box>
  <box top_left_x="144" top_left_y="479" bottom_right_x="1155" bottom_right_y="604">
  <type>Expéditeur_organisme / Dactylographié</type>
  <text>L.M.A.R.C.\nLaboratoire de Mécanique Appliquée R. Chaléat</text>
  </box>
  <box top_left_x="144" top_left_y="604" bottom_right_x="815" bottom_right_y="773">
  <type>Expéditeur_autre / Dactylographié</type>
  <text>UMR CNRS 6604\n24 rue de l'Epitaphe\n25000 BESANCON (FRANCE)</text>
  </box>
  <box top_left_x="144" top_left_y="778" bottom_right_x="487" bottom_right_y="834">
  <type>Expéditeur_autre / Dactylographié</type>
  <text>Tél. secrétariat :</text>
  </box>
  <box top_left_x="489" top_left_y="778" bottom_right_x="815" bottom_right_y="834">
  <type>Expéditeur_tél / Dactylographié</type>
  <text>03.81.66.60.00</text>
  </box>
  <box top_left_x="144" top_left_y="837" bottom_right_x="487" bottom_right_y="898">
  <type>Expéditeur_fax / Dactylographié</type>
  <text>Fax secrétariat :</text>
  </box>
  <box top_left_x="492" top_left_y="837" bottom_right_x="813" bottom_right_y="896">
  <type>Expéditeur_fax / Dactylographié</type>
  <text>03.81.66.67.00</text>
  </box>
  <box top_left_x="1275" top_left_y="476" bottom_right_x="1414" bottom_right_y="548">
  <type>Date, Lieu / Dactylographié</type>
  <text>Date :</text>
  </box>
  <box top_left_x="1273" top_left_y="586" bottom_right_x="1976" bottom_right_y="663">
  <type>Autre / Dactylographié</type>
  <text>Nombre de page (inclus celle-ci) :</text>
  </box>
  <box top_left_x="1278" top_left_y="714" bottom_right_x="1535" bottom_right_y="786">
  <type>Expéditeur_autre / Dactylographié</type>
  <text>Expéditeur :</text>
  </box>
  <box top_left_x="1275" top_left_y="834" bottom_right_x="1404" bottom_right_y="898">
  <type>Expéditeur_autre / Dactylographié</type>
  <text>Tél. :</text>
  </box>
  <box top_left_x="144" top_left_y="925" bottom_right_x="433" bottom_right_y="987">
  <type>Destinataire_autre / Dactylographié</type>
  <text>Destinataire :</text>
  </box>
  <box top_left_x="142" top_left_y="1101" bottom_right_x="260" bottom_right_y="1158">
  <type>Destinataire_autre / Dactylographié</type>
  <text>Fax :</text>
  </box>
  <box top_left_x="1428" top_left_y="465" bottom_right_x="1693" bottom_right_y="553">
  <type>Date, Lieu / Manuscrit</type>
  <text>05/10/06</text>
  </box>
  <box top_left_x="1981" top_left_y="575" bottom_right_x="2068" bottom_right_y="656">
  <type>Autre / Manuscrit</type>
  <text>3</text>
  </box>
  <box top_left_x="1551" top_left_y="679" bottom_right_x="2084" bottom_right_y="771">
  <type>Expéditeur_personne / Manuscrit</type>
  <text>Gérard LONGUET</text>
  </box>
  <box top_left_x="1412" top_left_y="813" bottom_right_x="1904" bottom_right_y="909">
  <type>Expéditeur_tél / Manuscrit</type>
  <text>03 00 06 18 86</text>
  </box>
  <box top_left_x="444" top_left_y="928" bottom_right_x="946" bottom_right_y="992">
  <type>Destinataire_organisme / Manuscrit</type>
  <text>MANIF Assurances</text>
  </box>
  <box top_left_x="347" top_left_y="1091" bottom_right_x="886" bottom_right_y="1175">
  <type>Destinataire_fax / Manuscrit</type>
  <text>01 60 76 43 33</text>
  </box>
  <box top_left_x="176" top_left_y="1290" bottom_right_x="399" bottom_right_y="1419">
  <type>Objet / Manuscrit</type>
  <text>Objet :</text>
  </box>
  <box top_left_x="406" top_left_y="1286" bottom_right_x="1433" bottom_right_y="1391">
  <type>Objet / Manuscrit</type>
  <text>résiliation d'assurance automobile</text>
  </box>
</annotation>
