<?xml version="1.0" encoding="utf-8"?>
<!DOCTYPE annotation SYSTEM "annotation.dtd">
<annotation date="18/12/2007" author="Jouve">
  <source width="2467" height="3502">00642_Q.png</source>
  <document>Questionnaire</document>
  <scenario>Changement de données personnelles</scenario>
  <writer>MORO Odile</writer>
  <sender_person></sender_person>
  <sender_company></sender_company>
  <sender_tel></sender_tel>
  <sender_fax></sender_fax>
  <receiver_person></receiver_person>
  <receiver_company></receiver_company>
  <subject></subject>
  <date></date>
  <place></place>
  <box top_left_x="175" top_left_y="378" bottom_right_x="732" bottom_right_y="521">
       <type>Code d'envoi</type>
       <text>PNPIXB</text>
  </box>
  <box top_left_x="405" top_left_y="542" bottom_right_x="1214" bottom_right_y="650">
       <type>Nom</type>
       <text>MORO</text>
  </box>
  <box top_left_x="1408" top_left_y="544" bottom_right_x="2181" bottom_right_y="650">
       <type>Prénom</type>
       <text>ODILE</text>
  </box>
  <box top_left_x="488" top_left_y="645" bottom_right_x="2186" bottom_right_y="745">
       <type>Adresse</type>
       <text>4 rue des jardins</text>
  </box>
  <box top_left_x="565" top_left_y="746" bottom_right_x="983" bottom_right_y="854">
       <type>Code Postal</type>
       <text>57270</text>
  </box>
  <box top_left_x="1105" top_left_y="742" bottom_right_x="2188" bottom_right_y="856">
       <type>Ville</type>
       <text>RICHEMONT</text>
  </box>
  <box top_left_x="372" top_left_y="858" bottom_right_x="1245" bottom_right_y="1008">
       <type>Téléphone</type>
       <text>0373339037</text>
  </box>
  <box top_left_x="511" top_left_y="1128" bottom_right_x="2187" bottom_right_y="1244">
       <type>Catégorie Scénario</type>
       <text>Changement de données personnelles</text>
  </box>
  <box top_left_x="295" top_left_y="1238" bottom_right_x="2187" bottom_right_y="1420">
       <type>Objet Scénario</type>
       <text>Nouvelles coordonnées téléphoniques\n</text>
  </box>
  <box top_left_x="287" top_left_y="1417" bottom_right_x="2187" bottom_right_y="1606">
       <type>Complément Scénario</type>
       <text>déménagement\n</text>
  </box>
  <box top_left_x="912" top_left_y="1625" bottom_right_x="1548" bottom_right_y="1774">
       <type>Référence client</type>
       <text>CZNUF04</text>
  </box>
  <box top_left_x="587" top_left_y="1773" bottom_right_x="2193" bottom_right_y="1868">
       <type>Interlocuteur</type>
       <text>Baqnue Crédit populaire</text>
  </box>
  <box top_left_x="499" top_left_y="1863" bottom_right_x="2191" bottom_right_y="1965">
       <type>Adresse Interlocuteur</type>
       <text>2 Rue Guynemer</text>
  </box>
  <box top_left_x="576" top_left_y="1961" bottom_right_x="1005" bottom_right_y="2080">
       <type>Code Postal Interlocuteur</type>
       <text>60190</text>
  </box>
  <box top_left_x="1139" top_left_y="1961" bottom_right_x="2193" bottom_right_y="2062">
       <type>Ville Interlocuteur</type>
       <text>ESTREES ST DENIS</text>
  </box>
  <box top_left_x="1057" top_left_y="2300" bottom_right_x="1272" bottom_right_y="2411">
       <type>Temps passé</type>
       <text>10</text>
  </box>
  <box top_left_x="891" top_left_y="2239" bottom_right_x="980" bottom_right_y="2306">
       <type>Stylo bille</type>
       <text>x</text>
  </box>
  <box top_left_x="1077" top_left_y="2235" bottom_right_x="1126" bottom_right_y="2287">
       <type>Stylo plume</type>
       <text></text>
  </box>
  <box top_left_x="1292" top_left_y="2235" bottom_right_x="1345" bottom_right_y="2287">
       <type>Stylo feutre</type>
       <text></text>
  </box>
  <box top_left_x="289" top_left_y="2705" bottom_right_x="364" bottom_right_y="2771">
       <type>Contribution postale</type>
       <text>x</text>
  </box>
  <box top_left_x="1599" top_left_y="2658" bottom_right_x="2198" bottom_right_y="2770">
       <type>Date d'envoi postal</type>
       <text></text>
  </box>
  <box top_left_x="307" top_left_y="2800" bottom_right_x="357" bottom_right_y="2848">
       <type>Option Page de garde de fax</type>
       <text></text>
  </box>
  <box top_left_x="306" top_left_y="2895" bottom_right_x="357" bottom_right_y="2941">
       <type>Option envoi par fax</type>
       <text></text>
  </box>
  <box top_left_x="1741" top_left_y="2832" bottom_right_x="2191" bottom_right_y="2949">
       <type>Date d'envoi par fax</type>
       <text></text>
  </box>
  <box top_left_x="306" top_left_y="2986" bottom_right_x="358" bottom_right_y="3036">
       <type>Option envoi par courriel</type>
       <text></text>
  </box>
  <box top_left_x="1597" top_left_y="2952" bottom_right_x="2193" bottom_right_y="3054">
       <type>Date d'envoi par courriel</type>
       <text></text>
  </box>
  <box top_left_x="1738" top_left_y="3149" bottom_right_x="2004" bottom_right_y="3244">
       <type>Résolution</type>
       <text></text>
  </box>
  <box top_left_x="579" top_left_y="3176" bottom_right_x="630" bottom_right_y="3226">
       <type>Format PNG</type>
       <text></text>
  </box>
  <box top_left_x="784" top_left_y="3176" bottom_right_x="836" bottom_right_y="3226">
       <type>Format GIF</type>
       <text></text>
  </box>
  <box top_left_x="965" top_left_y="3176" bottom_right_x="1015" bottom_right_y="3227">
       <type>Format TIFF</type>
       <text></text>
  </box>
  <box top_left_x="1076" top_left_y="3050" bottom_right_x="2194" bottom_right_y="3150">
       <type>Marque et modèle scanner</type>
       <text></text>
  </box>
</annotation>
