{
    "bank": "CREDIT AGRICOLE",
    "branch": "SUDOUEST",
    "amount_in_words": "Seven Thousand Three Hundred and Twenty Eight",
    "amount_in_numbers": 7328,
    "account_holder": "David Corbel",
    "reference": "FaabieF",
    "time": "12:5",
    "location": "Bordo",
    "transaction_code": "1aca1",
    "amount": 1200,
    "date": "06/05/22",
    "transaction_id": "EL.37",
    "address": "RueduCraPercre",
    "postal_code": "TOCTOL.CL3E",
    "check_number": "2581230",
    "phone_number": "0658985474125",
    "account_number": "369852369852"
}