{
    "Code d'envoi": "",
    "Nom": "PERONNET",
    "Prénom": "Killian",
    "Adresse": "13 rue de l'Eglise",
    "Code Postal": "57925",
    "Ville": "DISTROFF",
    "Téléphone": "0356929224",
    "Catégorie Scénario": "Demande d'information",
    "Objet Scénario": "Demande de rendez-vous avec conseiller\\n",
    "Complément Scénario": "Vous divorcez\\n",
    "Référence client": "ODYOK73",
    "Interlocuteur": "BMP - Banque Mutuelle de Paris",
    "Adresse Interlocuteur": "AVENUE GEORGES CLEMENCEAU",
    "Code Postal Interlocuteur": "73800",
    "Ville Interlocuteur": "MONTMELIAN",
    "Temps passé": "10",
    "Stylo bille": "",
    "Stylo plume": "",
    "Stylo feutre": "x",
    "Contribution postale": "x",
    "Date d'envoi postal": "04 octobre 2006",
    "Option Page de garde de fax": "",
    "Option envoi par fax": "",
    "Date d'envoi par fax": "",
    "Option envoi par courriel": "x",
    "Date d'envoi par courriel": "03/10/2006",
    "Résolution": "300",
    "Format PNG": "",
    "Format GIF": "",
    "Format TIFF": "x",
    "Marque et modèle scanner": "EPSON Stylus CX6600"
}