{
    "Code d'envoi": "SQFBKG",
    "Nom": "ADELINE",
    "Prénom": "Jessy",
    "Adresse": "58 rue des Vignes",
    "Code Postal": "67470",
    "Ville": "Wintzenbach",
    "Téléphone": "0332525724",
    "Catégorie Scénario": "Fermeture de compte",
    "Objet Scénario": "Résiliation d'assurance auto\\n",
    "Complément Scénario": "Vous êtes insatisfaite du service\\n",
    "Référence client": "RIGDY42",
    "Interlocuteur": "NNA Assurances",
    "Adresse Interlocuteur": "5 rue Charles Prieur",
    "Code Postal Interlocuteur": "49670",
    "Ville Interlocuteur": "Valanjou",
    "Temps passé": "25",
    "Stylo bille": "x",
    "Stylo plume": "",
    "Stylo feutre": "",
    "Contribution postale": "x",
    "Date d'envoi postal": "5/10/2006",
    "Option Page de garde de fax": "x",
    "Option envoi par fax": "x",
    "Date d'envoi par fax": "5/10/2006",
    "Option envoi par courriel": "x",
    "Date d'envoi par courriel": "5/10/2006",
    "Résolution": "300",
    "Format PNG": "x",
    "Format GIF": "",
    "Format TIFF": "",
    "Marque et modèle scanner": "HP 1510"
}