{
    "Code d'envoi": "RSOJPY",
    "Nom": "LAGUERRE",
    "Prénom": "Léna",
    "Adresse": "16 Rue Roger Siblot",
    "Code Postal": "39100",
    "Ville": "DOLE",
    "Téléphone": "0324552368",
    "Catégorie Scénario": "Ouverture de Compte",
    "Objet Scénario": "Vous souhaitez connaître la marche à\\nsuivre pour devenir client.",
    "Complément Scénario": "/\\n",
    "Référence client": "",
    "Interlocuteur": "",
    "Adresse Interlocuteur": "BOF Telecom",
    "Code Postal Interlocuteur": "62217",
    "Ville Interlocuteur": "ACHICOURT",
    "Temps passé": "20",
    "Stylo bille": "x",
    "Stylo plume": "",
    "Stylo feutre": "",
    "Contribution postale": "x",
    "Date d'envoi postal": "09 10 06",
    "Option Page de garde de fax": "x",
    "Option envoi par fax": "x",
    "Date d'envoi par fax": "09 10 06",
    "Option envoi par courriel": "x",
    "Date d'envoi par courriel": "07 10 06",
    "Résolution": "300",
    "Format PNG": "",
    "Format GIF": "",
    "Format TIFF": "x",
    "Marque et modèle scanner": "CANON MPC 200"
}