{
    "Code d'envoi": "OWRKJN",
    "Nom": "Paul",
    "Prénom": "Isabelle",
    "Adresse": "7, place Godard",
    "Code Postal": "25200",
    "Ville": "Grand Charmont",
    "Téléphone": "0399586376",
    "Catégorie Scénario": "fermeture de compte",
    "Objet Scénario": "résiliation d'assurance habitation\\n",
    "Complément Scénario": "vous êtes insatisfaite du service\\n",
    "Référence client": "RMPZH22",
    "Interlocuteur": "NNA Assurances",
    "Adresse Interlocuteur": "Village",
    "Code Postal Interlocuteur": "82370",
    "Ville Interlocuteur": "ORGUEIL",
    "Temps passé": "5",
    "Stylo bille": "",
    "Stylo plume": "",
    "Stylo feutre": "x",
    "Contribution postale": "x",
    "Date d'envoi postal": "9/10/06",
    "Option Page de garde de fax": "x",
    "Option envoi par fax": "",
    "Date d'envoi par fax": "",
    "Option envoi par courriel": "x",
    "Date d'envoi par courriel": "9/10/06",
    "Résolution": "300",
    "Format PNG": "x",
    "Format GIF": "",
    "Format TIFF": "",
    "Marque et modèle scanner": "CANON CANOSCANLIDE20"
}