{
    "Code d'envoi": "IFAGPL",
    "Nom": "PAYET",
    "Prénom": "Chantal",
    "Adresse": "1 La Landette",
    "Code Postal": "12160",
    "Ville": "Moyrazes",
    "Téléphone": "0522935531",
    "Catégorie Scénario": "Modification de contrat / Commande",
    "Objet Scénario": "Demande de mensualisation de l'impôt sur le revenu\\n",
    "Complément Scénario": "\\n",
    "Référence client": "MMELS89",
    "Interlocuteur": "Trésorerie des impôts",
    "Adresse Interlocuteur": "Le Bourg",
    "Code Postal Interlocuteur": "16460",
    "Ville Interlocuteur": "Aunac",
    "Temps passé": "15",
    "Stylo bille": "x",
    "Stylo plume": "",
    "Stylo feutre": "",
    "Contribution postale": "x",
    "Date d'envoi postal": "8/11/06",
    "Option Page de garde de fax": "",
    "Option envoi par fax": "",
    "Date d'envoi par fax": "",
    "Option envoi par courriel": "x",
    "Date d'envoi par courriel": "7/11/06",
    "Résolution": "200",
    "Format PNG": "",
    "Format GIF": "",
    "Format TIFF": "x",
    "Marque et modèle scanner": "Canonscan N676U"
}