{
    "Code d'envoi": "NGOYVR",
    "Nom": "CISSE",
    "Prénom": "BERTRAND",
    "Adresse": "32 RUE DE BALE",
    "Code Postal": "68580",
    "Ville": "SEPPOIS-LE-HAUT",
    "Téléphone": "0344683039",
    "Catégorie Scénario": "OUVERTURE DE COMPTE",
    "Objet Scénario": "VOUS SOUHAITEZ VOUS ABONNER\\n",
    "Complément Scénario": "VOUS AVEZ DAVANTAGE DE TEMPS\\nPOUR VOS LOISIRS",
    "Référence client": "",
    "Interlocuteur": "MENSUEL \" FLEURS & MERGUEZ \"",
    "Adresse Interlocuteur": "BOULEVARD D'ALSACE LORRAINE",
    "Code Postal Interlocuteur": "82202",
    "Ville Interlocuteur": "MOISSAC",
    "Temps passé": "10",
    "Stylo bille": "x",
    "Stylo plume": "",
    "Stylo feutre": "",
    "Contribution postale": "x",
    "Date d'envoi postal": "17.11.2006",
    "Option Page de garde de fax": "x",
    "Option envoi par fax": "",
    "Date d'envoi par fax": "",
    "Option envoi par courriel": "",
    "Date d'envoi par courriel": "",
    "Résolution": "",
    "Format PNG": "",
    "Format GIF": "",
    "Format TIFF": "",
    "Marque et modèle scanner": ""
}