{
    "Code d'envoi": "XHAQWI",
    "Nom": "JULIA",
    "Prénom": "Karine",
    "Adresse": "RES PRE de PAQUES BAT C N56",
    "Code Postal": "83170",
    "Ville": "BRIGNOLLES",
    "Téléphone": "0416810885",
    "Catégorie Scénario": "Gestion de sinistre",
    "Objet Scénario": "Vous souhaitez être couvert au titre de la\\nresponsabilité civile",
    "Complément Scénario": "vous aviez brisé la porte vitrée d'un\\nmagasin en passant au travers",
    "Référence client": "NWJR228",
    "Interlocuteur": "BAAF Assurances",
    "Adresse Interlocuteur": "rue Nationale",
    "Code Postal Interlocuteur": "41210",
    "Ville Interlocuteur": "La FERTE BEAUHARNAIS",
    "Temps passé": "15",
    "Stylo bille": "x",
    "Stylo plume": "",
    "Stylo feutre": "",
    "Contribution postale": "x",
    "Date d'envoi postal": "15/12/06",
    "Option Page de garde de fax": "",
    "Option envoi par fax": "",
    "Date d'envoi par fax": "",
    "Option envoi par courriel": "x",
    "Date d'envoi par courriel": "15/12/06",
    "Résolution": "300",
    "Format PNG": "x",
    "Format GIF": "",
    "Format TIFF": "",
    "Marque et modèle scanner": "HP 6300"
}