{
    "Code d'envoi": "SZLNZF",
    "Nom": "LEGRIX",
    "Prénom": "Isabelle",
    "Adresse": "3 RUE DE LA RITT",
    "Code Postal": "68640",
    "Ville": "STEINSOULTZ",
    "Téléphone": "0369742843",
    "Catégorie Scénario": "Modification de Contrat / Commande",
    "Objet Scénario": "Commande de trois paires de Chaussettes\\n(référence du produit : CH45-12)",
    "Complément Scénario": "aucun\\n",
    "Référence client": "CNDRU60",
    "Interlocuteur": "Les 3 Suifs",
    "Adresse Interlocuteur": "40 RUE JEAN BRINGER",
    "Code Postal Interlocuteur": "11000",
    "Ville Interlocuteur": "CARCASSONNE",
    "Temps passé": "20",
    "Stylo bille": "x",
    "Stylo plume": "",
    "Stylo feutre": "",
    "Contribution postale": "x",
    "Date d'envoi postal": "27/12/06",
    "Option Page de garde de fax": "",
    "Option envoi par fax": "",
    "Date d'envoi par fax": "",
    "Option envoi par courriel": "x",
    "Date d'envoi par courriel": "27/12/06",
    "Résolution": "300",
    "Format PNG": "",
    "Format GIF": "",
    "Format TIFF": "x",
    "Marque et modèle scanner": "TRUST Easy Connect 19200 plus"
}