<?xml version="1.0" encoding="utf-8"?>
<!DOCTYPE annotation SYSTEM "annotation.dtd">
<annotation date="19/12/2007" author="Jouve ">
  <source width="2476" height="3511">03959_L.png</source>
  <document>Lettre manuscrite</document>
  <scenario>Modification de contrat / Commande</scenario>
  <writer>FITOUSSI Gilles</writer>
  <sender_person>Mr Fitoussi Gilles</sender_person>
  <sender_company></sender_company>
  <sender_tel>+33(0)3.94.64.84.22</sender_tel>
  <sender_fax></sender_fax>
  <receiver_person></receiver_person>
  <receiver_company>La Reboute</receiver_company>
  <subject>Objet : Augmentation (x2) des quantités\nde chaussettes commandées</subject>
  <date>20/03/2007</date>
  <place></place>
  <box top_left_x="27" top_left_y="34" bottom_right_x="971" bottom_right_y="468">
  <type>Coordonnées Expéditeur</type>
  <text>Mr Fitoussi Gilles\n28 rue Raymond Queneau\n51370 St Brice Courcelles\n03 94 64 84 22</text>
  </box>
  <box top_left_x="1718" top_left_y="46" bottom_right_x="2442" bottom_right_y="387">
  <type>Coordonnées Destinataire</type>
  <text>La Reboute\n24 rue Maréchal Foch\n65400 Argeles Gazost</text>
  </box>
  <box top_left_x="77" top_left_y="592" bottom_right_x="1355" bottom_right_y="858">
  <type>Objet</type>
  <text>Objet : Augmentation (x2) des quantités\nde chaussettes commandées</text>
  </box>
  <box top_left_x="81" top_left_y="867" bottom_right_x="778" bottom_right_y="1002">
  <type>Coordonnées Expéditeur</type>
  <text>Référence : TBNVO68</text>
  </box>
  <box top_left_x="1447" top_left_y="913" bottom_right_x="2090" bottom_right_y="1064">
  <type>Date, Lieu</type>
  <text>Le 20 Mars 2007,</text>
  </box>
  <box top_left_x="824" top_left_y="1111" bottom_right_x="1540" bottom_right_y="1269">
  <type>Ouverture</type>
  <text>Madame, Monsieur,</text>
  </box>
  <box top_left_x="58" top_left_y="1300" bottom_right_x="2462" bottom_right_y="2020">
  <type>Corps de texte</type>
  <text>Je vous prie de bien vouloir modifier la quantité de\nchaussettes que je vous ai commandé lors de ma récente commande.\nEn effet, je souhaite commander deux paires de chaussettes\nau lieu d'une.\nJe vous remercie par avance pour la prise en compte de\nma demande.</text>
  </box>
  <box top_left_x="1409" top_left_y="2048" bottom_right_x="2195" bottom_right_y="2423">
  <type>Signature</type>
  <text></text>
  </box>
</annotation>
