<?xml version="1.0" encoding="utf-8"?>
<!DOCTYPE annotation SYSTEM "annotation.dtd">
<annotation date="19/12/2007" author="Jouve ">
  <source width="2479" height="3508">04275_L.png</source>
  <document>Lettre manuscrite</document>
  <scenario>Réclamation</scenario>
  <writer>MATTEI Adele</writer>
  <sender_person>MATTEI Adèle</sender_person>
  <sender_company></sender_company>
  <sender_tel>+33(0)3.43.36.29.77</sender_tel>
  <sender_fax></sender_fax>
  <receiver_person></receiver_person>
  <receiver_company>Les 3 Suifs</receiver_company>
  <subject>Objet : Demande de remboursement</subject>
  <date>16/03/2007</date>
  <place>VENTRON</place>
  <box top_left_x="15" top_left_y="11" bottom_right_x="968" bottom_right_y="541">
  <type>Coordonnées Expéditeur</type>
  <text>MATTEI Adèle\n10 bis PLANOIS DE LA CHAPELLE\n88310 VENTRON\n03 43 36 29 77\n¤{Ref./Réf.}¤ Client : FRRH148</text>
  </box>
  <box top_left_x="1647" top_left_y="26" bottom_right_x="2318" bottom_right_y="381">
  <type>Coordonnées Destinataire</type>
  <text>Les 3 Suifs\n6, rue de la MALRUE\n89520 SAINTS</text>
  </box>
  <box top_left_x="11" top_left_y="587" bottom_right_x="1056" bottom_right_y="728">
  <type>Objet</type>
  <text>Objet : Demande de remboursement</text>
  </box>
  <box top_left_x="1464" top_left_y="900" bottom_right_x="2311" bottom_right_y="1037">
  <type>Date, Lieu</type>
  <text>VENTRON, le 16 mars 2007</text>
  </box>
  <box top_left_x="430" top_left_y="1269" bottom_right_x="1025" bottom_right_y="1437">
  <type>Ouverture</type>
  <text>Madame, Monsieur,</text>
  </box>
  <box top_left_x="7" top_left_y="1472" bottom_right_x="2456" bottom_right_y="2791">
  <type>Corps de texte</type>
  <text>Je soussignée HATEI Adèle vous contacte suite à une\ncommande ¤{recemment/récemment}¤ passée sur votre catalogue et que je viens de\nreçevoir.\nJ'ai en effet le regret de constater que l'aspirateur\nque j'ai acheté ne fonctionne pas lorsque je le branche.\nC'est la raison pour laquelle je vous demande un rembour-\nsement de cet objet défectueux, que je vous renverrai sous peu.\nVeuillez agréer Madame, Monsieur, l'expression de mes\nsalutations distinguées.</text>
  </box>
  <box top_left_x="1433" top_left_y="2875" bottom_right_x="2116" bottom_right_y="3138">
  <type>Signature</type>
  <text></text>
  </box>
</annotation>
