<?xml version="1.0" encoding="utf-8"?>
<!DOCTYPE annotation SYSTEM "annotation.dtd">
<annotation date="19/12/2007" author="Jouve ">
  <source width="2476" height="3509">05446_L.png</source>
  <document>Lettre manuscrite</document>
  <scenario>Demande d'information</scenario>
  <writer>PERONNET Diane</writer>
  <sender_person>PERONNET Diane</sender_person>
  <sender_company></sender_company>
  <sender_tel>+33(0)3.25.57.60.85</sender_tel>
  <sender_fax></sender_fax>
  <receiver_person></receiver_person>
  <receiver_company>ANPE\Agence Nationale pour l'Emploi</receiver_company>
  <date>27/09/2007</date>
  <place>Lobsann</place>
  <box top_left_x="68" top_left_y="114" bottom_right_x="1054" bottom_right_y="523">
  <type>Coordonnées Expéditeur</type>
  <text>PERONNET Diane\n25 Route de Marionbronn\n67 250 LOBSANN\n03 25 57 60 85</text>
  </box>
  <box top_left_x="1383" top_left_y="657" bottom_right_x="2472" bottom_right_y="1184">
  <type>Coordonnées Destinataire</type>
  <text>ANPE\nAgence Nationale pour l'Emploi\nRoute de Blancafort\nCernoy en BERRY\n45 360 CERNOY en BERRY</text>
  </box>
  <box top_left_x="1409" top_left_y="1215" bottom_right_x="2273" bottom_right_y="1474">
  <type>Date, Lieu</type>
  <text>A Lobsann,\nLe 27 Septembre 2007,</text>
  </box>
  <box top_left_x="263" top_left_y="1505" bottom_right_x="680" bottom_right_y="1604">
  <type>Ouverture</type>
  <text>Monsieur,</text>
  </box>
  <box top_left_x="636" top_left_y="1592" bottom_right_x="658" bottom_right_y="1619">
  <type>Ouverture</type>
  <text></text>
  </box>
  <box top_left_x="202" top_left_y="1621" bottom_right_x="2475" bottom_right_y="3192">
  <type>Corps de texte</type>
  <text>Je me suis inscrite auprès de votre agence le 03 Mars 2007\nsous la référence MZHTR 18 et je suis suivie par Monsieur\nDUMOULINS. Chaque mois je reçois donc ma convocation pour \nfaire le bilan et m'y rends comme vous avez pu le constater. Or ce mois-ci j'en reçois deux ! Une venant de la DDTTE et une venant de Monsieur DUMOULINS. Ces deux courriers me convoquent à deux jours d'intervalle. Il est regrettable que\nvos services ne puissent fonctionner de manière coordonnée.\nVous comprendrez certainement que ces déplacements répétitifs\ncontraints freinent ma recherche d'emploi et qu'au vu de mon\nbudget limité je juge plus utile de garder de l'essence pour \naller à un entretien ou démarcher un employeur.\nJe souhaite donc convenir d'un entretien avec vous dans\nun délai raisonnable pour en reparler et faire le point sur\nma situation. Merci également de faire le nécessaire auprès\nde la DDTTE afin d'annuler le rendez-vous et éviter une ¤radiation¤\nVeuillez recevoir, Monsieur, mes salutations.</text>
  </box>
  <box top_left_x="1635" top_left_y="3200" bottom_right_x="2261" bottom_right_y="3477">
  <type>Signature</type>
  <text></text>
  </box>
</annotation>
