<?xml version="1.0" encoding="utf-8"?>
<!DOCTYPE annotation SYSTEM "annotation.dtd">
<annotation date="19/12/2007" author="Jouve">
  <source width="2475" height="3508">05592_Q.png</source>
  <document>Questionnaire</document>
  <scenario>Difficulté de paiement</scenario>
  <writer>LE GALL Delphine</writer>
  <sender_person></sender_person>
  <sender_company></sender_company>
  <sender_tel></sender_tel>
  <sender_fax></sender_fax>
  <receiver_person></receiver_person>
  <receiver_company></receiver_company>
  <subject></subject>
  <date></date>
  <place></place>
  <box top_left_x="174" top_left_y="363" bottom_right_x="731" bottom_right_y="506">
       <type>Code d'envoi</type>
       <text>KXAXAG</text>
  </box>
  <box top_left_x="405" top_left_y="525" bottom_right_x="1213" bottom_right_y="632">
       <type>Nom</type>
       <text>LE GALL</text>
  </box>
  <box top_left_x="1406" top_left_y="523" bottom_right_x="2179" bottom_right_y="627">
       <type>Prénom</type>
       <text>Delphine</text>
  </box>
  <box top_left_x="488" top_left_y="626" bottom_right_x="2184" bottom_right_y="722">
       <type>Adresse</type>
       <text>38 rue Principale</text>
  </box>
  <box top_left_x="565" top_left_y="729" bottom_right_x="984" bottom_right_y="836">
       <type>Code Postal</type>
       <text>67690</text>
  </box>
  <box top_left_x="1105" top_left_y="723" bottom_right_x="2188" bottom_right_y="832">
       <type>Ville</type>
       <text>HATTEN</text>
  </box>
  <box top_left_x="374" top_left_y="842" bottom_right_x="1245" bottom_right_y="988">
       <type>Téléphone</type>
       <text>0301704715</text>
  </box>
  <box top_left_x="514" top_left_y="1106" bottom_right_x="2188" bottom_right_y="1225">
       <type>Catégorie Scénario</type>
       <text>Difficulté de paiement</text>
  </box>
  <box top_left_x="298" top_left_y="1217" bottom_right_x="2188" bottom_right_y="1402">
       <type>Objet Scénario</type>
       <text>Demande de remise gracieuse\n</text>
  </box>
  <box top_left_x="291" top_left_y="1397" bottom_right_x="2188" bottom_right_y="1586">
       <type>Complément Scénario</type>
       <text>Vous venez de perdre votre emploi\n</text>
  </box>
  <box top_left_x="915" top_left_y="1605" bottom_right_x="1551" bottom_right_y="1754">
       <type>Référence client</type>
       <text>SFGPD02</text>
  </box>
  <box top_left_x="591" top_left_y="1752" bottom_right_x="2196" bottom_right_y="1848">
       <type>Interlocuteur</type>
       <text>GDF</text>
  </box>
  <box top_left_x="502" top_left_y="1842" bottom_right_x="2196" bottom_right_y="1947">
       <type>Adresse Interlocuteur</type>
       <text>CHEF LIEU</text>
  </box>
  <box top_left_x="580" top_left_y="1942" bottom_right_x="1009" bottom_right_y="2061">
       <type>Code Postal Interlocuteur</type>
       <text>38580</text>
  </box>
  <box top_left_x="1143" top_left_y="1940" bottom_right_x="2196" bottom_right_y="2041">
       <type>Ville Interlocuteur</type>
       <text>LA CHAPELLE DU BARD</text>
  </box>
  <box top_left_x="1061" top_left_y="2279" bottom_right_x="1276" bottom_right_y="2389">
       <type>Temps passé</type>
       <text>25</text>
  </box>
  <box top_left_x="883" top_left_y="2218" bottom_right_x="957" bottom_right_y="2268">
       <type>Stylo bille</type>
       <text>x</text>
  </box>
  <box top_left_x="1082" top_left_y="2214" bottom_right_x="1130" bottom_right_y="2266">
       <type>Stylo plume</type>
       <text></text>
  </box>
  <box top_left_x="1296" top_left_y="2214" bottom_right_x="1348" bottom_right_y="2266">
       <type>Stylo feutre</type>
       <text></text>
  </box>
  <box top_left_x="313" top_left_y="2687" bottom_right_x="390" bottom_right_y="2737">
       <type>Contribution postale</type>
       <text>x</text>
  </box>
  <box top_left_x="1604" top_left_y="2634" bottom_right_x="2203" bottom_right_y="2747">
       <type>Date d'envoi postal</type>
       <text>15 mai 2007</text>
  </box>
  <box top_left_x="314" top_left_y="2782" bottom_right_x="363" bottom_right_y="2830">
       <type>Option Page de garde de fax</type>
       <text></text>
  </box>
  <box top_left_x="312" top_left_y="2877" bottom_right_x="364" bottom_right_y="2923">
       <type>Option envoi par fax</type>
       <text></text>
  </box>
  <box top_left_x="1747" top_left_y="2807" bottom_right_x="2197" bottom_right_y="2926">
       <type>Date d'envoi par fax</type>
       <text></text>
  </box>
  <box top_left_x="313" top_left_y="2969" bottom_right_x="365" bottom_right_y="3018">
       <type>Option envoi par courriel</type>
       <text></text>
  </box>
  <box top_left_x="1603" top_left_y="2928" bottom_right_x="2199" bottom_right_y="3032">
       <type>Date d'envoi par courriel</type>
       <text></text>
  </box>
  <box top_left_x="1745" top_left_y="3125" bottom_right_x="2010" bottom_right_y="3220">
       <type>Résolution</type>
       <text></text>
  </box>
  <box top_left_x="586" top_left_y="3157" bottom_right_x="637" bottom_right_y="3207">
       <type>Format PNG</type>
       <text></text>
  </box>
  <box top_left_x="791" top_left_y="3156" bottom_right_x="843" bottom_right_y="3206">
       <type>Format GIF</type>
       <text></text>
  </box>
  <box top_left_x="972" top_left_y="3155" bottom_right_x="1022" bottom_right_y="3206">
       <type>Format TIFF</type>
       <text></text>
  </box>
  <box top_left_x="1083" top_left_y="3026" bottom_right_x="2201" bottom_right_y="3129">
       <type>Marque et modèle scanner</type>
       <text></text>
  </box>
</annotation>
