{
    "BLACKMARKET": {
        "MARKET_OVERVIEW": {
            "CURRENT_SITUATION": null,
            "GEOGRAPHIC_CONCENTRATION": null,
            "FUTURE_OUTLOOK": null
        },
        "REVIEW_OF_CIGARETTE_MARKET": {
            "COMPETITIVE_ENVIRONMENT": null,
            "COMPANY_CATEGORY_SEGMENT_PERFORMANCE": null,
            "SHARE_AND_TREND": "RTR/MATOR_COMPETITION"
        },
        "REVIEW_OF_THE_CONSUMER": {
            "DEMOGRAPHIC_PROFILE": null,
            "PURCHASE_PATTERNS": null,
            "PRODUCT_IMAGE_WANTS": null,
            "LIFESTYLES_ACTIVITIES_HOBBIES": null,
            "BRAND_PERCEPTIONS": null,
            "BRAND_FAMILIARITY": null
        },
        "SUMMARY": {
            "BUSINESS_OPPORTUNITY_IMPLICATIONS": null
        }
    },
    "numbers": [
        50339,
        2653
    ]
}