{
    "code": "56-L5",
    "details": [
        {
            "id": "2527-20",
            "fe": "FE040s/Ft-00S",
            "fv": "FV-065",
            "mn": "mn-mm-18oo"
        },
        {
            "id": "2527-25",
            "fe": "Fe: 050s/ft0505",
            "fv": "FV-osos",
            "mx": "mx-mmz.-/805"
        },
        {
            "id": "12527-204",
            "fe": "FE-04.05/FT0405",
            "fv": "FV-D405",
            "mx": "mx.-mmz/804"
        },
        {
            "id": "1257-03",
            "fg": "FG-0305/FT0305",
            "fv": "FV.-0305",
            "mx": "mx-mz-/80o3"
        },
        {
            "id": "125276202",
            "fg": "FG:0205./FT0205",
            "fv": "FV-.0Z05",
            "m": "m-mmz-182"
        },
        {
            "id": "12527-401",
            "fe": "FE0105FT0105",
            "fv": "FV-0105",
            "mixer": "MIxER-mz-800!"
        }
    ],
    "note": "NOTEABOE SPMSASSOCBATWTH THANSPOKTG.CORNSYR FROM.HOLOG.TAK.TO.ACHMXG",
    "contact": {
        "omlesms": "CO",
        "deptpp": "ese7",
        "fax1": "983-17/8",
        "fax2": "741-7773",
        "code1": "51217",
        "code2": "4729"
    }
}