{
    "id": "338d0",
    "name": "R, J. Reanoldo Promotions",
    "recent_purchase": "peromeeCtreTanRTop.wf3pack",
    "issue": "did not receive the tank back (as guaranteed in the package) because my husband settled the tank for our location",
    "action": "waiting for another one in the meantime",
    "contact": {
        "phone": "805-964-8870",
        "address": {
            "street": "15740 E Aue Q-40",
            "city": "Palmdale",
            "state": "CA",
            "zip": "93591"
        }
    },
    "reference_number": "518304362"
}