{
    "e-I": "82-0013",
    "22790": "AREA",
    "8": "DCG",
    "PROPOSED_CHANGE_FORM": {
        "1": {
            "Originator": "H.WActma/s.SHAkeRi"
        },
        "2": {
            "Proposed_Change_to": [
                "A Parameters",
                "B Standards",
                "C Control Moves"
            ]
        },
        "3": {
            "Problem_Statement": "VARiATN iN RFiNR SeA WATR.FW RATe CAusEs ReFiwing VARiAtO an FREENSS ARyNG is NoT sciFieD. BCAuse"
        },
        "4": {
            "List_evidence": "CRiGAC FWmeTs SCALe is ON TiCKLcR ReFiweRs ARe DNy IGpm. Too sma.Top oF ANdseTat FwmaTe 1.5GPmFo HAs B in PlAcc AppRox G.mos."
        },
        "5": {
            "VARiATiON": "is the objective? Who is the customer? 1.) yieb - RducTio iN Fsh wnTen ito PRocess. O.V. 3aston"
        },
        "6": {
            "Identify_probable_causes_of_problem": "PRoPeR Flow is Not speciFied. 2. Flww metes Aeeto sml."
        },
        "7": {
            "Describe_proposed_SPC_system_change": "Powmetens ONR 13 WATen FUw To AcH PAcKiNg GLAND StNDAD a1.5Gm."
        },
        "8": {
            "Recommend_measurements_of_effectiveness_of_proposed_change": ""
        },
        "9": {
            "Describe_action_plan_for_implementing_proposed_change": "attach if need more spacean apprvd STeam Contactinmpated pursonnel upon impiementhm. SC"
        },
        "10": {
            "List_personnel_impacted": [
                "MA SenicrCps4",
                "MR Supv4",
                "2050371761",
                "SPCSpecialists",
                "ATud",
                "R.Mcmik",
                "Area Mat. Sn"
            ]
        }
    }
}