{
    "facsimileTransmission": {
        "office": "Washington Relations Office",
        "address": {
            "street": "1341 G Street, NW",
            "suite": "Suite 900",
            "city": "Washington",
            "state": "DC",
            "zip": "20005"
        },
        "phone": "202637-1500",
        "recipients": [
            "Cheryl Comes",
            "Chris Mohrmann"
        ],
        "cc": [
            "J. Lenzi",
            "J. MeDaniel"
        ],
        "from": "Dan Smith",
        "tel": "(202)637-1502",
        "fax": "202737-2093",
        "date": "April 3, 1998",
        "comments": "FINALBILI",
        "additionalInfo": {
            "contact": "Heather Erskine",
            "contactPhone": "202/637-1568"
        },
        "message": {
            "id": "2064899281",
            "subject": "Wisconsin-S.313",
            "details": "Wisconsin-S.313 was amended in the Assembly, approved and concurred in by the Senate. On its way to the Governor for consideration, the measure now has three provisions only: allows an increase in the retailer tobacco license fee up to $100, restricts vending machines to taverns and adult-only facilities and restricts sampling to adult-only or adult-restricted locations."
        }
    }
}