{
    "title": "Hawaii Philip Morris 'Takedown' Report",
    "company": "Outdoor Company Copy",
    "date": "4/23/99",
    "task": "TA5K0",
    "market": "Island of Maui",
    "state": "HI",
    "location": "",
    "vendor": "Outdoor Systems",
    "mediaType": "Mall Dioramas",
    "banos": "Yes",
    "postedOver": "Whited Out",
    "extensionsInPlace": "Only 19648",
    "destroyedRemainingCopy": "Yes",
    "removedCopyBeneathVinyl": "No",
    "notesComments": "",
    "gmSalesManagerSignature": "",
    "dateOfCopyRemoval": "",
    "completionPhotoInstructions": "Please send a completion photo and copy of this report to your Starcom representative.",
    "contactNumber": "2084617439"
}