{
    "terminate": "If terminated, send raw data to RAQA Archives",
    "reject": [
        "Circle Ont",
        "Ae"
    ],
    "significantEffect": "No significant effect",
    "studyDirectorRecommendations": "No significant effect",
    "divisionDirector": "Check One",
    "directorOfRAQA": "Check Ont",
    "recommendations": "DEVIATION REPORT",
    "sponsorContact": "X",
    "contacted": "--",
    "comments": [
        "q",
        "6",
        "Comments:",
        "Comments:",
        ".6",
        "3",
        "p",
        "(",
        "To+!mg",
        "een"
    ],
    "microbiologicalAssociates": "QPT0I0",
    "additionalSheets": "Attach additional sheets as necessary",
    "location": "Merytand20816",
    "code": "68",
    "number": "2390",
    "reporterInstructions": "Reporter fills in Items 1-7",
    "dateOfObservation": "",
    "documentNumber": "",
    "natureOfDeviation": "",
    "detailedDescription": "",
    "reasonForDeviation": "0",
    "studyNumbers": "",
    "kindOfStudy": "---",
    "specificProtocol": "",
    "studyDirector": "10",
    "unknownField": "6",
    "unknownNumber": "88994116"
}