{
    "Code d'envoi": "YHKOSI",
    "Nom": "BOITEL",
    "Prénom": "Myriam",
    "Adresse": "21 rue de la Forêt",
    "Code Postal": "67250",
    "Ville": "SCHOENENBOURG",
    "Téléphone": "0327700734",
    "Catégorie Scénario": "Gestion de sinistre",
    "Objet Scénario": "Vous faites appel à votre assurance\\nautomobile",
    "Complément Scénario": "Vous avez provoqué un accident de la\\nroute (vous déclarerez joindre le constat)",
    "Référence client": "SZJHF93",
    "Interlocuteur": "NAIF Assurances",
    "Adresse Interlocuteur": "4 rue des Carlets",
    "Code Postal Interlocuteur": "35520",
    "Ville Interlocuteur": "La Chapelle des Fargenetz",
    "Temps passé": "45",
    "Stylo bille": "x",
    "Stylo plume": "",
    "Stylo feutre": "",
    "Contribution postale": "x",
    "Date d'envoi postal": "23/03/07",
    "Option Page de garde de fax": "",
    "Option envoi par fax": "x",
    "Date d'envoi par fax": "23/03/07",
    "Option envoi par courriel": "x",
    "Date d'envoi par courriel": "23/03/07",
    "Résolution": "300",
    "Format PNG": "",
    "Format GIF": "",
    "Format TIFF": "x",
    "Marque et modèle scanner": "HEWLETT PACKARD OFFICE JET G55"
}