{
    "Code d'envoi": "SWUWCV",
    "Nom": "RENARD",
    "Prénom": "RODOLPHE",
    "Adresse": "7 rue du chene",
    "Code Postal": "57690",
    "Ville": "FLETRANGE",
    "Téléphone": "0350744884",
    "Catégorie Scénario": "Relance de courrier sans réponse",
    "Objet Scénario": "Votre demande de résiliation du mois\\ndernier n'a pas été prise en compte",
    "Complément Scénario": "aucun\\n",
    "Référence client": "OZQKM45",
    "Interlocuteur": "EDF",
    "Adresse Interlocuteur": "18 et 20 avenue Robert Daugey",
    "Code Postal Interlocuteur": "13080",
    "Ville Interlocuteur": "LUYNES",
    "Temps passé": "20",
    "Stylo bille": "x",
    "Stylo plume": "",
    "Stylo feutre": "",
    "Contribution postale": "x",
    "Date d'envoi postal": "",
    "Option Page de garde de fax": "",
    "Option envoi par fax": "",
    "Date d'envoi par fax": "",
    "Option envoi par courriel": "x",
    "Date d'envoi par courriel": "",
    "Résolution": "",
    "Format PNG": "x",
    "Format GIF": "",
    "Format TIFF": "",
    "Marque et modèle scanner": "HP PSC 1350"
}