{
    "Code d'envoi": "OWLBYF",
    "Nom": "MARTINET",
    "Prénom": "Edith",
    "Adresse": "31 rue de La gare",
    "Code Postal": "57330",
    "Ville": "ZOUFFTGEN",
    "Téléphone": "0363269113",
    "Catégorie Scénario": "Modification de contrat/Commande",
    "Objet Scénario": "Commande de trois paires de chaussettes\\n(référence du produit : CH4-5-12)",
    "Complément Scénario": "aucun\\n",
    "Référence client": "MFXIN28",
    "Interlocuteur": "Les 3 Suifs",
    "Adresse Interlocuteur": "Centre Cial Elysees II",
    "Code Postal Interlocuteur": "78170",
    "Ville Interlocuteur": "LA CELLE ST CLOUD",
    "Temps passé": "",
    "Stylo bille": "x",
    "Stylo plume": "",
    "Stylo feutre": "",
    "Contribution postale": "x",
    "Date d'envoi postal": "2/04/07",
    "Option Page de garde de fax": "x",
    "Option envoi par fax": "",
    "Date d'envoi par fax": "",
    "Option envoi par courriel": "x",
    "Date d'envoi par courriel": "1/04/07",
    "Résolution": "200",
    "Format PNG": "",
    "Format GIF": "",
    "Format TIFF": "x",
    "Marque et modèle scanner": "Lexmark X1190"
}