{
    "Code d'envoi": "UTOKGU",
    "Nom": "CARADEC",
    "Prénom": "MEDMI",
    "Adresse": "1 RUE DE RUSTENHART",
    "Code Postal": "68600",
    "Ville": "DESSENHEIM",
    "Téléphone": "0374941404",
    "Catégorie Scénario": "Gestion de sinistre",
    "Objet Scénario": "vous êtes sans nouvelles concernant l'expertise de\\nvotre ¤{vehicule/véhicule}¤ accidenté le mois dernier",
    "Complément Scénario": "Aucun\\n",
    "Référence client": "IKHZ¤Y¤36",
    "Interlocuteur": "BAAF Assurances",
    "Adresse Interlocuteur": "Rue de La Croix 52130 VOILLE COMTE",
    "Code Postal Interlocuteur": "52130",
    "Ville Interlocuteur": "VOILLE COMTE",
    "Temps passé": "20",
    "Stylo bille": "x",
    "Stylo plume": "",
    "Stylo feutre": "",
    "Contribution postale": "x",
    "Date d'envoi postal": "30/3/07",
    "Option Page de garde de fax": "",
    "Option envoi par fax": "",
    "Date d'envoi par fax": "",
    "Option envoi par courriel": "x",
    "Date d'envoi par courriel": "30/3/07",
    "Résolution": "",
    "Format PNG": "",
    "Format GIF": "x",
    "Format TIFF": "",
    "Marque et modèle scanner": "MP 730 CANON"
}