{
    "document": "Lettre manuscrite",
    "scenario": "Gestion de sinistre",
    "writer": "LOUIS Sara",
    "sender_person": "LOUIS Sara",
    "sender_company": "",
    "sender_tel": "+33(0)1.78.56.41.34",
    "sender_fax": "",
    "receiver_person": "",
    "receiver_company": "NNA Assurances",
    "subject": "Objet : Lettre recommandée avec\\naccusé de réception\\nDéclaration de sinistre\\n(accident de la route)\\nréf client : JWP DV24",
    "date": "19/04/2007",
    "place": "",
    "box": ""
}