{
    "Code d'envoi": "CGOXNP",
    "Nom": "Ansquer",
    "Prénom": "Thomas",
    "Adresse": "58 Rue de Galpingue",
    "Code Postal": "68720",
    "Ville": "Spechbech le haut",
    "Téléphone": "0352043025",
    "Catégorie Scénario": "Gestion de sinistre",
    "Objet Scénario": "SANS Nouvelle de l'expertise\\n",
    "Complément Scénario": "\\n",
    "Référence client": "WDYST67",
    "Interlocuteur": "NNA ASSURANCES",
    "Adresse Interlocuteur": "",
    "Code Postal Interlocuteur": "74560",
    "Ville Interlocuteur": "Monnetier Mor¤nex¤",
    "Temps passé": "15",
    "Stylo bille": "x",
    "Stylo plume": "",
    "Stylo feutre": "",
    "Contribution postale": "x",
    "Date d'envoi postal": "25/04/07",
    "Option Page de garde de fax": "x",
    "Option envoi par fax": "",
    "Date d'envoi par fax": "",
    "Option envoi par courriel": "x",
    "Date d'envoi par courriel": "25/04/07",
    "Résolution": "300",
    "Format PNG": "",
    "Format GIF": "",
    "Format TIFF": "x",
    "Marque et modèle scanner": ""
}