{
    "Code d'envoi": "BMTEUV",
    "Nom": "MICHAUX",
    "Prénom": "Hélène",
    "Adresse": "240 rue Salvador Allende",
    "Code Postal": "54230",
    "Ville": "Neuves Maisons",
    "Téléphone": "0378810449",
    "Catégorie Scénario": "Demande d'information",
    "Objet Scénario": "Demande de rendez-vous avec un conseiller\\n",
    "Complément Scénario": "Vous venez de perdre votre emploi\\n",
    "Référence client": "YXWAR04",
    "Interlocuteur": "Banque Débit Lyonnais",
    "Adresse Interlocuteur": "",
    "Code Postal Interlocuteur": "24100",
    "Ville Interlocuteur": "Bergerac",
    "Temps passé": "6",
    "Stylo bille": "x",
    "Stylo plume": "",
    "Stylo feutre": "",
    "Contribution postale": "x",
    "Date d'envoi postal": "30/04/07",
    "Option Page de garde de fax": "",
    "Option envoi par fax": "",
    "Date d'envoi par fax": "",
    "Option envoi par courriel": "x",
    "Date d'envoi par courriel": "29/04/07",
    "Résolution": "200",
    "Format PNG": "x",
    "Format GIF": "",
    "Format TIFF": "",
    "Marque et modèle scanner": "Epson Stylus Photo RX 500"
}