{
    "Code d'envoi": "GRUJMV",
    "Nom": "BERTEAUX",
    "Prénom": "Logan",
    "Adresse": "13 CHEMIN DU ROUAU",
    "Code Postal": "54160",
    "Ville": "PIERREVILLE",
    "Téléphone": "0316745863",
    "Catégorie Scénario": "Changement de données personnelles",
    "Objet Scénario": "Nouvelles coordonnées téléphoniques\\n",
    "Complément Scénario": "Vous vous installez avec votre conjoint\\n",
    "Référence client": "XHBUG94",
    "Interlocuteur": "BAAF Assurances",
    "Adresse Interlocuteur": "21 RUE DU BOIS DE LA CHAMPELLE",
    "Code Postal Interlocuteur": "54500",
    "Ville Interlocuteur": "VANDOEUVRE LES NANCY",
    "Temps passé": "7",
    "Stylo bille": "x",
    "Stylo plume": "",
    "Stylo feutre": "",
    "Contribution postale": "x",
    "Date d'envoi postal": "16-05-07",
    "Option Page de garde de fax": "x",
    "Option envoi par fax": "x",
    "Date d'envoi par fax": "16-05-07",
    "Option envoi par courriel": "x",
    "Date d'envoi par courriel": "16-05-07",
    "Résolution": "200",
    "Format PNG": "",
    "Format GIF": "",
    "Format TIFF": "x",
    "Marque et modèle scanner": "CANON CANOSCAN LIDE 70"
}